Project 2/clockDivider.v
module clockDivider(clock_in, reset_n, divide_by, clock_out);
input clock_in;
input reset_n;
input [31:0] divide_by;
output reg clock_out;

reg [22:0] clock_divider = 0;

initial begin
  clock_out = 0;
  clock_divider = 0;
end
always @(posedge clock_in or negedge reset_n)
  begin
    if (~reset_n)
      begin
        clock_out = 0;
        clock_divider = 0;
      end
    else
      begin
        if(clock_divider != divide_by - 1)
          clock_divider <= clock_divider + 1;
        else
          begin
            clock_divider <= 0;
            clock_out <= ~clock_out;
          end
      end
  end
endmodule

Project 2/sevenSeg.v
// ALTERED SEVEN SEG so that there is blanking and no letters. See project 1 for real SevenSeg module
module sevenSeg (input [3:0] val, output reg [7:0] seg, output reg [7:0] seg1);

always @(val)
  begin
    case(val[3:0])
      4'b0000 : seg = 8'b11000000;
      4'b0001 : seg = 8'b11111001;
      4'b0010 : seg = 8'b10100100;
      4'b0011 : seg = 8'b10110000;
      4'b0100 : seg = 8'b10011001;
      4'b0101 : seg = 8'b10010010;
      4'b0110 : seg = 8'b10000010;
      4'b0111 : seg = 8'b11111000;
      4'b1000 : seg = 8'b10000000;
      4'b1001 : seg = 8'b10011000;

      //Code to blank the display
      4'b1111 : seg = 8'b11111111;
      default : seg = 8'b11111111;
    endcase
  end
endmodule

Project 2/counter.v
module counter(clock, reset_n, counter10, counter1, segCounter10);

input clock;
input reset_n;
output [3:0] counter10;
output [3:0] counter1;
output [3:0] segCounter10;

reg [3:0] c10;
reg [3:0] c1;
reg [3:0] sC10;

assign counter10 = c10;
assign counter1 = c1;
assign segCounter10 = sC10;

initial begin
    c1 = 0;
    c10 = 0;
    sC10 = 4'b1111;
end

always @ (negedge clock or negedge reset_n)
    begin
       if (~reset_n)
       begin
            c1 <= 1;
            c10 <= 0;
            sC10 <= 4'b1111;
        end
        else
        begin
            if (c1 != 4'b1001)
            begin
                c1 <= c1 + 1;
            end
            else
            begin
                if (c10 != 4'b1001)
                begin
                    c1 <= 0;
                    c10 <= c10 + 1;
                    sC10 <= c10 + 1;
                end
                else
                begin
                    c1 <= 1;
                    c10 <= 0;
                    sC10 <= 4'b1111;
                end
            end
        end
    end

endmodule

Project 2/top.v
module top (ADC_CLK_10, KEY, HEX0, HEX1, HEX2, HEX4, HEX5, LEDR);

input ADC_CLK_10;
input [1:0] KEY;

output [7:0] HEX0;
output [7:0] HEX1;
output [7:0] HEX2;
output [7:0] HEX4;
output [7:0] HEX5;
output [9:0] LEDR;

wire clock;
reg clock_reset;
wire [3:0] counter1;
wire [3:0] counter10;
wire [3:0] segCounter10;
reg ledValue;
reg [31:0] divide_by;

assign LEDR[9:1] = 9'b0_0000_0000;
assign LEDR[0] = ledValue;

counter C0(.clock(clock), .reset_n(KEY[0]), .counter10(counter10), .counter1(counter1), .segCounter10(segCounter10));
sevenSeg H4 (.val(counter1), .seg(HEX4));
sevenSeg H5 (.val(segCounter10), .seg(HEX5));
clockDivider U0 (.clock_in(ADC_CLK_10), .divide_by(divide_by), .reset_n(KEY[0]), .clock_out(clock));

initial begin
    ledValue = 0;
    divide_by = 2500000;
end

always @ (negedge clock or negedge KEY[0])
    begin
       if (~KEY[0])
            ledValue = 0;
        else
            ledValue <= ~ledValue;

    end

always @ (negedge clock or negedge KEY[1]) begin
  if(~KEY[1])
    divide_by = 1250000;
  else
    divide_by = 2500000;
end
endmodule

Project 2/tbtop.v
`timescale 1 ns / 100 ps

module tbtop();

reg [9:0] testSW;
reg [1:0] testKEY;
reg clock;
reg [7:0] counter;
wire [9:0] testLED;
wire [7:0] testHEX0;
wire [7:0] testHEX1;
wire [7:0] testHEX2;
wire [7:0] testHEX3;
wire [7:0] testHEX4;
wire [7:0] testHEX5;

top DUT(.KEY(testKEY), .ADC_CLK_10(clock), .LEDR(testLED),.HEX0(testHEX0),.HEX1(testHEX1),.HEX2(testHEX2),.HEX4(testHEX4),.HEX5(testHEX5));

// Begin stimulating inputs:
initial begin
  $dumpfile("test.vcd");
  $dumpvars;
  $display($time, "Starting simulation");

  //Initialize inputs:
  testSW = 10'b0000000000;
  testKEY = 1;
  clock = 1'b0;
  counter = 0;
  while(counter < 8'b11111111) begin
    #10 clock = ~clock;
    counter = counter + 1;
  end
  // End testing
  #10 $finish;
end

// Monitor inputs and outputs
initial
  begin
    $monitor($time, "testSW = %b, testKEY = %b, clock = %b, testLED = %b, testHEX0 = %b, testHEX1 = %b, testHEX2 = %b, testHEX3 = %b, testHEX4 = %b, testHEX5 = %b",
           testSW, testKEY, testLED, clock, testHEX0, testHEX1, testHEX2, testHEX3, testHEX4, testHEX5);
  end
endmodule

Project 2/test.vcd
$date
	Fri Feb 28 11:05:52 2020
$end
$version
	Icarus Verilog
$end
$timescale
	100ps
$end
$scope module tbtop $end
$var wire 8 ! testHEX0 [7:0] $end
$var wire 8 " testHEX1 [7:0] $end
$var wire 8 # testHEX2 [7:0] $end
$var wire 8 $ testHEX3 [7:0] $end
$var wire 10 % testLED [9:0] $end
$var wire 8 & testHEX5 [7:0] $end
$var wire 8 ' testHEX4 [7:0] $end
$var reg 1 ( clock $end
$var reg 8 ) counter [7:0] $end
$var reg 2 * testKEY [1:0] $end
$var reg 10 + testSW [9:0] $end
$scope module DUT $end
$var wire 1 ( ADC_CLK_10 $end
$var wire 8 , HEX0 [7:0] $end
$var wire 8 - HEX1 [7:0] $end
$var wire 8 . HEX2 [7:0] $end
$var wire 2 / KEY [1:0] $end
$var wire 4 0 segCounter10 [3:0] $end
$var wire 4 1 counter10 [3:0] $end
$var wire 4 2 counter1 [3:0] $end
$var wire 1 3 clock $end
$var wire 10 4 LEDR [9:0] $end
$var wire 8 5 HEX5 [7:0] $end
$var wire 8 6 HEX4 [7:0] $end
$var reg 32 7 divide_by [31:0] $end
$var reg 1 8 ledValue $end
$scope module C0 $end
$var wire 4 9 counter1 [3:0] $end
$var wire 4 : counter10 [3:0] $end
$var wire 1 ; reset_n $end
$var wire 4 < segCounter10 [3:0] $end
$var wire 1 3 clock $end
$var reg 4 = c1 [3:0] $end
$var reg 4 > c10 [3:0] $end
$var reg 4 ? sC10 [3:0] $end
$upscope $end
$scope module H4 $end
$var wire 4 @ val [3:0] $end
$var reg 8 A seg [7:0] $end
$var reg 8 B seg1 [7:0] $end
$upscope $end
$scope module H5 $end
$var wire 4 C val [3:0] $end
$var reg 8 D seg [7:0] $end
$var reg 8 E seg1 [7:0] $end
$upscope $end
$scope module U0 $end
$var wire 1 ( clock_in $end
$var wire 32 F divide_by [31:0] $end
$var wire 1 G reset_n $end
$var reg 23 H clock_divider [22:0] $end
$var reg 1 3 clock_out $end
$upscope $end
$upscope $end
$upscope $end
$enddefinitions $end
#0
$dumpvars
b0 H
1G
b100110001001011010000 F
bx E
b11111111 D
b1111 C
bx B
b11111001 A
b1 @
b1111 ?
b0 >
b1 =
b1111 <
1;
b0 :
b1 9
08
b100110001001011010000 7
b11111001 6
b11111111 5
b0 4
03
b1 2
b0 1
b1111 0
b1 /
bz .
bz -
bz ,
b0 +
b1 *
b0 )
0(
b11111001 '
b11111111 &
b0 %
bz $
bz #
bz "
bz !
$end
#100
b1 H
b1 )
1(
#200
b10 )
0(
#300
b10 H
b11 )
1(
#400
b100 )
0(
#500
b11 H
b101 )
1(
#600
b110 )
0(
#700
b100 H
b111 )
1(
#800
b1000 )
0(
#900
b101 H
b1001 )
1(
#1000
b1010 )
0(
#1100
b110 H
b1011 )
1(
#1200
b1100 )
0(
#1300
b111 H
b1101 )
1(
#1400
b1110 )
0(
#1500
b1000 H
b1111 )
1(
#1600
b10000 )
0(
#1700
b1001 H
b10001 )
1(
#1800
b10010 )
0(
#1900
b1010 H
b10011 )
1(
#2000
b10100 )
0(
#2100
b1011 H
b10101 )
1(
#2200
b10110 )
0(
#2300
b1100 H
b10111 )
1(
#2400
b11000 )
0(
#2500
b1101 H
b11001 )
1(
#2600
b11010 )
0(
#2700
b1110 H
b11011 )
1(
#2800
b11100 )
0(
#2900
b1111 H
b11101 )
1(
#3000
b11110 )
0(
#3100
b10000 H
b11111 )
1(
#3200
b100000 )
0(
#3300
b10001 H
b100001 )
1(
#3400
b100010 )
0(
#3500
b10010 H
b100011 )
1(
#3600
b100100 )
0(
#3700
b10011 H
b100101 )
1(
#3800
b100110 )
0(
#3900
b10100 H
b100111 )
1(
#4000
b101000 )
0(
#4100
b10101 H
b101001 )
1(
#4200
b101010 )
0(
#4300
b10110 H
b101011 )
1(
#4400
b101100 )
0(
#4500
b10111 H
b101101 )
1(
#4600
b101110 )
0(
#4700
b11000 H
b101111 )
1(
#4800
b110000 )
0(
#4900
b11001 H
b110001 )
1(
#5000
b110010 )
0(
#5100
b11010 H
b110011 )
1(
#5200
b110100 )
0(
#5300
b11011 H
b110101 )
1(
#5400
b110110 )
0(
#5500
b11100 H
b110111 )
1(
#5600
b111000 )
0(
#5700
b11101 H
b111001 )
1(
#5800
b111010 )
0(
#5900
b11110 H
b111011 )
1(
#6000
b111100 )
0(
#6100
b11111 H
b111101 )
1(
#6200
b111110 )
0(
#6300
b100000 H
b111111 )
1(
#6400
b1000000 )
0(
#6500
b100001 H
b1000001 )
1(
#6600
b1000010 )
0(
#6700
b100010 H
b1000011 )
1(
#6800
b1000100 )
0(
#6900
b100011 H
b1000101 )
1(
#7000
b1000110 )
0(
#7100
b100100 H
b1000111 )
1(
#7200
b1001000 )
0(
#7300
b100101 H
b1001001 )
1(
#7400
b1001010 )
0(
#7500
b100110 H
b1001011 )
1(
#7600
b1001100 )
0(
#7700
b100111 H
b1001101 )
1(
#7800
b1001110 )
0(
#7900
b101000 H
b1001111 )
1(
#8000
b1010000 )
0(
#8100
b101001 H
b1010001 )
1(
#8200
b1010010 )
0(
#8300
b101010 H
b1010011 )
1(
#8400
b1010100 )
0(
#8500
b101011 H
b1010101 )
1(
#8600
b1010110 )
0(
#8700
b101100 H
b1010111 )
1(
#8800
b1011000 )
0(
#8900
b101101 H
b1011001 )
1(
#9000
b1011010 )
0(
#9100
b101110 H
b1011011 )
1(
#9200
b1011100 )
0(
#9300
b101111 H
b1011101 )
1(
#9400
b1011110 )
0(
#9500
b110000 H
b1011111 )
1(
#9600
b1100000 )
0(
#9700
b110001 H
b1100001 )
1(
#9800
b1100010 )
0(
#9900
b110010 H
b1100011 )
1(
#10000
b1100100 )
0(
#10100
b110011 H
b1100101 )
1(
#10200
b1100110 )
0(
#10300
b110100 H
b1100111 )
1(
#10400
b1101000 )
0(
#10500
b110101 H
b1101001 )
1(
#10600
b1101010 )
0(
#10700
b110110 H
b1101011 )
1(
#10800
b1101100 )
0(
#10900
b110111 H
b1101101 )
1(
#11000
b1101110 )
0(
#11100
b111000 H
b1101111 )
1(
#11200
b1110000 )
0(
#11300
b111001 H
b1110001 )
1(
#11400
b1110010 )
0(
#11500
b111010 H
b1110011 )
1(
#11600
b1110100 )
0(
#11700
b111011 H
b1110101 )
1(
#11800
b1110110 )
0(
#11900
b111100 H
b1110111 )
1(
#12000
b1111000 )
0(
#12100
b111101 H
b1111001 )
1(
#12200
b1111010 )
0(
#12300
b111110 H
b1111011 )
1(
#12400
b1111100 )
0(
#12500
b111111 H
b1111101 )
1(
#12600
b1111110 )
0(
#12700
b1000000 H
b1111111 )
1(
#12800
b10000000 )
0(
#12900
b1000001 H
b10000001 )
1(
#13000
b10000010 )
0(
#13100
b1000010 H
b10000011 )
1(
#13200
b10000100 )
0(
#13300
b1000011 H
b10000101 )
1(
#13400
b10000110 )
0(
#13500
b1000100 H
b10000111 )
1(
#13600
b10001000 )
0(
#13700
b1000101 H
b10001001 )
1(
#13800
b10001010 )
0(
#13900
b1000110 H
b10001011 )
1(
#14000
b10001100 )
0(
#14100
b1000111 H
b10001101 )
1(
#14200
b10001110 )
0(
#14300
b1001000 H
b10001111 )
1(
#14400
b10010000 )
0(
#14500
b1001001 H
b10010001 )
1(
#14600
b10010010 )
0(
#14700
b1001010 H
b10010011 )
1(
#14800
b10010100 )
0(
#14900
b1001011 H
b10010101 )
1(
#15000
b10010110 )
0(
#15100
b1001100 H
b10010111 )
1(
#15200
b10011000 )
0(
#15300
b1001101 H
b10011001 )
1(
#15400
b10011010 )
0(
#15500
b1001110 H
b10011011 )
1(
#15600
b10011100 )
0(
#15700
b1001111 H
b10011101 )
1(
#15800
b10011110 )
0(
#15900
b1010000 H
b10011111 )
1(
#16000
b10100000 )
0(
#16100
b1010001 H
b10100001 )
1(
#16200
b10100010 )
0(
#16300
b1010010 H
b10100011 )
1(
#16400
b10100100 )
0(
#16500
b1010011 H
b10100101 )
1(
#16600
b10100110 )
0(
#16700
b1010100 H
b10100111 )
1(
#16800
b10101000 )
0(
#16900
b1010101 H
b10101001 )
1(
#17000
b10101010 )
0(
#17100
b1010110 H
b10101011 )
1(
#17200
b10101100 )
0(
#17300
b1010111 H
b10101101 )
1(
#17400
b10101110 )
0(
#17500
b1011000 H
b10101111 )
1(
#17600
b10110000 )
0(
#17700
b1011001 H
b10110001 )
1(
#17800
b10110010 )
0(
#17900
b1011010 H
b10110011 )
1(
#18000
b10110100 )
0(
#18100
b1011011 H
b10110101 )
1(
#18200
b10110110 )
0(
#18300
b1011100 H
b10110111 )
1(
#18400
b10111000 )
0(
#18500
b1011101 H
b10111001 )
1(
#18600
b10111010 )
0(
#18700
b1011110 H
b10111011 )
1(
#18800
b10111100 )
0(
#18900
b1011111 H
b10111101 )
1(
#19000
b10111110 )
0(
#19100
b1100000 H
b10111111 )
1(
#19200
b11000000 )
0(
#19300
b1100001 H
b11000001 )
1(
#19400
b11000010 )
0(
#19500
b1100010 H
b11000011 )
1(
#19600
b11000100 )
0(
#19700
b1100011 H
b11000101 )
1(
#19800
b11000110 )
0(
#19900
b1100100 H
b11000111 )
1(
#20000
b11001000 )
0(
#20100
b1100101 H
b11001001 )
1(
#20200
b11001010 )
0(
#20300
b1100110 H
b11001011 )
1(
#20400
b11001100 )
0(
#20500
b1100111 H
b11001101 )
1(
#20600
b11001110 )
0(
#20700
b1101000 H
b11001111 )
1(
#20800
b11010000 )
0(
#20900
b1101001 H
b11010001 )
1(
#21000
b11010010 )
0(
#21100
b1101010 H
b11010011 )
1(
#21200
b11010100 )
0(
#21300
b1101011 H
b11010101 )
1(
#21400
b11010110 )
0(
#21500
b1101100 H
b11010111 )
1(
#21600
b11011000 )
0(
#21700
b1101101 H
b11011001 )
1(
#21800
b11011010 )
0(
#21900
b1101110 H
b11011011 )
1(
#22000
b11011100 )
0(
#22100
b1101111 H
b11011101 )
1(
#22200
b11011110 )
0(
#22300
b1110000 H
b11011111 )
1(
#22400
b11100000 )
0(
#22500
b1110001 H
b11100001 )
1(
#22600
b11100010 )
0(
#22700
b1110010 H
b11100011 )
1(
#22800
b11100100 )
0(
#22900
b1110011 H
b11100101 )
1(
#23000
b11100110 )
0(
#23100
b1110100 H
b11100111 )
1(
#23200
b11101000 )
0(
#23300
b1110101 H
b11101001 )
1(
#23400
b11101010 )
0(
#23500
b1110110 H
b11101011 )
1(
#23600
b11101100 )
0(
#23700
b1110111 H
b11101101 )
1(
#23800
b11101110 )
0(
#23900
b1111000 H
b11101111 )
1(
#24000
b11110000 )
0(
#24100
b1111001 H
b11110001 )
1(
#24200
b11110010 )
0(
#24300
b1111010 H
b11110011 )
1(
#24400
b11110100 )
0(
#24500
b1111011 H
b11110101 )
1(
#24600
b11110110 )
0(
#24700
b1111100 H
b11110111 )
1(
#24800
b11111000 )
0(
#24900
b1111101 H
b11111001 )
1(
#25000
b11111010 )
0(
#25100
b1111110 H
b11111011 )
1(
#25200
b11111100 )
0(
#25300
b1111111 H
b11111101 )
1(
#25400
b11111110 )
0(
#25500
b10000000 H
b11111111 )
1(
