Project 2/top.v
module top (SW, KEY, ADC_CLK_10, LEDR, HEX0, HEX1, HEX2, HEX3, HEX4, HEX5);

input [9:0] SW;
input [1:0] KEY;
input ADC_CLK_10;
output reg [9:0] LEDR;
output reg [7:0] HEX0;
output reg [7:0] HEX1;
output reg [7:0] HEX2;
output reg [7:0] HEX3;
output reg [7:0] HEX4;
output reg [7:0] HEX5;

reg [7:0]count;

initial begin
   count = 8'b0000_0001;
   LEDR[9:1] = 8'b0000_0000;
end

always @(posedge ADC_CLK_10 or posedge KEY[0]) begin
  LEDR[0] = ~LEDR[0];
  if(KEY[0])
    count = 1;
  else
    count = count + 1;
end

endmodule

Project 2/tbtop.v
`timescale 1 ns / 100 ps

module tbtop();

reg [9:0] testSW;
reg [1:0] testKEY;
reg clock;
reg [3:0] counter;
wire [9:0] testLED;
wire [7:0] testHEX0;
wire [7:0] testHEX1;
wire [7:0] testHEX2;
wire [7:0] testHEX3;
wire [7:0] testHEX4;
wire [7:0] testHEX5;

top DUT(.SW(testSW), .KEY(testKEY), .ADC_CLK_10(clock), .LEDR(testLED),.HEX0(testHEX0),.HEX1(testHEX1),.HEX2(testHEX2),.HEX3(testHEX3),.HEX4(testHEX4),.HEX5(testHEX5));

// Begin stimulating inputs:
initial begin
  $dumpfile("test.vcd");
  $dumpvars;
  $display($time, "Starting simulation");

  //Initialize inputs:
  testSW = 10'b0000000000;
  testKEY = 2'b00;
  clock = 1'b0;
  counter = 0;
  while(counter < 4'b1111) begin
    #10 clock = ~clock;
    counter = counter + 1;
  end
  // End testing
  #10 $finish;
end

// Monitor inputs and outputs
initial
  begin
    $monitor($time, "testSW = %b, testKEY = %b, clock = %b, testLED = %b, testHEX0 = %b, testHEX1 = %b, testHEX2 = %b, testHEX3 = %b, testHEX4 = %b, testHEX5 = %b",
           testSW, testKEY, testLED, clock, testHEX0, testHEX1, testHEX2, testHEX3, testHEX4, testHEX5);
  end
endmodule

Project 2/test.vcd
$date
	Thu Feb 20 15:54:11 2020
$end
$version
	Icarus Verilog
$end
$timescale
	100ps
$end
$scope module tbtop $end
$var wire 10 ! testLED [9:0] $end
$var wire 8 " testHEX5 [7:0] $end
$var wire 8 # testHEX4 [7:0] $end
$var wire 8 $ testHEX3 [7:0] $end
$var wire 8 % testHEX2 [7:0] $end
$var wire 8 & testHEX1 [7:0] $end
$var wire 8 ' testHEX0 [7:0] $end
$var reg 1 ( clock $end
$var reg 4 ) counter [3:0] $end
$var reg 2 * testKEY [1:0] $end
$var reg 10 + testSW [9:0] $end
$scope module DUT $end
$var wire 1 ( ADC_CLK_10 $end
$var wire 2 , KEY [1:0] $end
$var wire 10 - SW [9:0] $end
$var reg 8 . HEX0 [7:0] $end
$var reg 8 / HEX1 [7:0] $end
$var reg 8 0 HEX2 [7:0] $end
$var reg 8 1 HEX3 [7:0] $end
$var reg 8 2 HEX4 [7:0] $end
$var reg 8 3 HEX5 [7:0] $end
$var reg 10 4 LEDR [9:0] $end
$var reg 8 5 count [7:0] $end
$upscope $end
$upscope $end
$enddefinitions $end
#0
$dumpvars
b1 5
b0x 4
bx 3
bx 2
bx 1
bx 0
bx /
bx .
b0 -
b0 ,
b0 +
b0 *
b0 )
0(
bx '
bx &
bx %
bx $
bx #
bx "
b0x !
$end
#100
b10 5
b1 )
1(
#200
b10 )
0(
#300
b11 5
b11 )
1(
#400
b100 )
0(
#500
b100 5
b101 )
1(
#600
b110 )
0(
#700
b101 5
b111 )
1(
#800
b1000 )
0(
#900
b110 5
b1001 )
1(
#1000
b1010 )
0(
#1100
b111 5
b1011 )
1(
#1200
b1100 )
0(
#1300
b1000 5
b1101 )
1(
#1400
b1110 )
0(
#1500
b1001 5
b1111 )
1(
