Project 2/clockDivider.v
module clockDivider(clock_in, reset_n, clock_out);
input clock_in;
input reset_n;
output reg clock_out;

reg [22:0] clock_divider = 0;
parameter divide_by = 2500000;
initial begin
  clock_out = 0;
  clock_divider = 0;
end
always @(posedge clock_in or negedge reset_n)
  begin
    if (~reset_n)
      begin
        clock_out = 0;
        clock_divider = 0;
      end
    else
      begin
        if(clock_divider != divide_by - 1)
          clock_divider <= clock_divider + 1;
        else
          begin
            clock_divider <= 0;
            clock_out <= ~clock_out;
          end
      end
  end
endmodule

Project 2/sevenSeg.v
// ALTERED SEVEN SEG so that there is blanking and no letters. See project 1 for real SevenSeg module
module sevenSeg (input [3:0] val, output reg [7:0] seg, output reg [7:0] seg1);

always @(val)
  begin
    case(val[3:0])
      4'b0000 : seg = 8'b11000000;
      4'b0001 : seg = 8'b11111001;
      4'b0010 : seg = 8'b10100100;
      4'b0011 : seg = 8'b10110000;
      4'b0100 : seg = 8'b10011001;
      4'b0101 : seg = 8'b10010010;
      4'b0110 : seg = 8'b10000010;
      4'b0111 : seg = 8'b11111000;
      4'b1000 : seg = 8'b10000000;
      4'b1001 : seg = 8'b10011000;

      //Code to blank the display
      4'b1111 : seg = 8'b11111111;
      default : seg = 8'b11111111;
    endcase
  end
endmodule

Project 2/calendar.v
module calendar (clock, reset_n, SW9, c10, c1, hm,  hd10, hd1);

input clock;
input reset_n;
input SW9;
input [3:0] c10;
input [3:0] c1;

output reg [3:0] hm;
output reg [3:0] hd1;
output reg [3:0] hd10;

wire [6:0] binary_c;
assign binary_c = c10*10+c1;

initial begin
  hm = 1;
  hd1 = 1;
  hd10 = 0;
end

always @(negedge clock or negedge reset_n)
  begin
    if(~reset_n)
      begin
        hm <= 1;
        hd1 <= 1;
        hd10 <= 0;
      end
    if(binary_c == 1)

      begin
        hm <= 1;
        hd1 <= 1;
        hd10 <= 0;
      end

    else if(binary_c != 1 & binary_c < 31)

      begin
        hm <= 1;
        if(hd1 != 9)
          hd1 <= hd1 + 1;
        else if(hd1 == 9)
        begin
          hd1 <= 0;
          hd10 <= hd10 +1;
        end

      end

    else if (binary_c == 32)

    begin
      hm <= 2;
      hd1 <= 1;
      hd10 <= 0;
    end

    else if(binary_c != 32 & binary_c < 59+SW9)

    begin
      if(hd1 == 9)
      begin
        hd1 <= 0;
        hd10 <= hd10 +1;
      end
      else
      begin
        hd1 <= hd1 + 1;
      end
      hm <= 2;
    end

  end
endmodule

Project 2/counter.v
module counter(clock, reset_n, c10, c1, sC10);

input clock;
input reset_n;

output reg [3:0] c10;
output reg [3:0] c1;
output reg [3:0] sC10;

// assign counter10 = c10;
// assign counter1 = c1;
// assign segCounter10 = sC10;

initial begin
    c1 = 0;
    c10 = 0;
    sC10 = 4'b1111;
end

always @ (negedge clock or negedge reset_n)
    begin
      if (~reset_n)
       begin
            c1 <= 1;
            c10 <= 0;
            sC10 <= 4'b1111;
        end
        else
        begin
            if (c1 != 4'b1001)
            begin
                c1 <= c1 + 1;
            end
            else
            begin
                if (c10 != 4'b1001)
                begin
                    c1 <= 0;
                    c10 <= c10 + 1;
                    sC10 <= c10 + 1;
                end
                else
                begin
                    c1 <= 1;
                    c10 <= 0;
                    sC10 <= 4'b1111;
                end
            end
        end
    end

endmodule

Project 2/top.v
module top (ADC_CLK_10, SW, KEY, HEX0, HEX1, HEX2, HEX4, HEX5, LEDR);

input ADC_CLK_10;
input [1:0] KEY;
input [9:0] SW;

output [7:0] HEX0;
output [7:0] HEX1;
output [7:0] HEX2;
output [7:0] HEX4;
output [7:0] HEX5;
output [9:0] LEDR;

wire clock;
reg clock_reset;
wire [3:0] counter1;
wire [3:0] counter10;
wire [3:0] segCounter10;
wire [3:0] hexMonth;
wire [3:0] hexDay1;
wire [3:0] hexDay10;
reg ledValue;
reg [31:0] divide_by;

assign LEDR[9:1] = 9'b0_0000_0000;
assign LEDR[0] = ledValue;

counter C0(.clock(clock), .reset_n(KEY[0]), .c10(counter10), .c1(counter1), .sC10(segCounter10));

calendar Cal0 (.clock(clock), .reset_n(KEY[0]), .SW9(SW[9]), .c10(counter10), .c1(counter1), .hm(hexMonth),  .hd10(hexDay10), .hd1(hexDay1));

sevenSeg H0 (.val(hexDay1), .seg(HEX0));
sevenSeg H1 (.val(hexDay10), .seg(HEX1));
sevenSeg H2 (.val(hexMonth), .seg(HEX2));

sevenSeg H4 (.val(counter1), .seg(HEX4));
sevenSeg H5 (.val(segCounter10), .seg(HEX5));
clockDivider U0 (.clock_in(ADC_CLK_10), .divide_by(divide_by), .reset_n(KEY[0]), .clock_out(clock));

initial begin
    ledValue = 0;
    divide_by = 2500000;
    // divide_by = 2;
end

always @ (negedge clock or negedge KEY[0])
    begin
       if (~KEY[0])
            ledValue = 0;
        else
            ledValue <= ~ledValue;

    end

always @ (negedge clock or negedge KEY[1]) begin
  if(~KEY[1])
    divide_by = 1000000;
    // divide_by = 1;
  else
    divide_by = 2500000;
    // divide_by = 2;
end
endmodule

Project 2/tbtop.v
`timescale 1 ns / 100 ps

module tbtop();

reg [9:0] testSW;
reg [1:0] testKEY;
reg clock;
reg [7:0] counter;
wire [9:0] testLED;
wire [7:0] testHEX0;
wire [7:0] testHEX1;
wire [7:0] testHEX2;
wire [7:0] testHEX3;
wire [7:0] testHEX4;
wire [7:0] testHEX5;

top DUT(.KEY(testKEY), .SW(testSW), .ADC_CLK_10(clock), .LEDR(testLED),.HEX0(testHEX0),.HEX1(testHEX1),.HEX2(testHEX2),.HEX4(testHEX4),.HEX5(testHEX5));

// Begin stimulating inputs:
initial begin
  $dumpfile("test.vcd");
  $dumpvars;
  $display($time, "Starting simulation");

  //Initialize inputs:
  testSW = 10'b0000000000;
  testKEY = 1;
  clock = 1'b0;
  counter = 0;
  while(counter < 8'b11111111) begin
    #10 clock = ~clock;
    counter = counter + 1;
  end
  // End testing
  #10 $finish;
end

// Monitor inputs and outputs
initial
  begin
    $monitor($time, "testSW = %b, testKEY = %b, clock = %b, testLED = %b, testHEX0 = %b, testHEX1 = %b, testHEX2 = %b, testHEX3 = %b, testHEX4 = %b, testHEX5 = %b",
           testSW, testKEY, testLED, clock, testHEX0, testHEX1, testHEX2, testHEX3, testHEX4, testHEX5);
  end
endmodule

Project 2/test.vcd
$date
	Thu Mar  5 16:35:09 2020
$end
$version
	Icarus Verilog
$end
$timescale
	100ps
$end
$scope module tbtop $end
$var wire 8 ! testHEX3 [7:0] $end
$var wire 10 " testLED [9:0] $end
$var wire 8 # testHEX5 [7:0] $end
$var wire 8 $ testHEX4 [7:0] $end
$var wire 8 % testHEX2 [7:0] $end
$var wire 8 & testHEX1 [7:0] $end
$var wire 8 ' testHEX0 [7:0] $end
$var reg 1 ( clock $end
$var reg 8 ) counter [7:0] $end
$var reg 2 * testKEY [1:0] $end
$var reg 10 + testSW [9:0] $end
$scope module DUT $end
$var wire 1 ( ADC_CLK_10 $end
$var wire 2 , KEY [1:0] $end
$var wire 10 - SW [9:0] $end
$var wire 4 . segCounter10 [3:0] $end
$var wire 4 / hexMonth [3:0] $end
$var wire 4 0 hexDay10 [3:0] $end
$var wire 4 1 hexDay1 [3:0] $end
$var wire 4 2 counter10 [3:0] $end
$var wire 4 3 counter1 [3:0] $end
$var wire 1 4 clock $end
$var wire 10 5 LEDR [9:0] $end
$var wire 8 6 HEX5 [7:0] $end
$var wire 8 7 HEX4 [7:0] $end
$var wire 8 8 HEX2 [7:0] $end
$var wire 8 9 HEX1 [7:0] $end
$var wire 8 : HEX0 [7:0] $end
$var reg 32 ; divide_by [31:0] $end
$var reg 1 < ledValue $end
$scope module C0 $end
$var wire 1 = reset_n $end
$var wire 1 4 clock $end
$var reg 4 > c1 [3:0] $end
$var reg 4 ? c10 [3:0] $end
$var reg 4 @ sC10 [3:0] $end
$upscope $end
$scope module Cal0 $end
$var wire 1 A SW9 $end
$var wire 4 B c1 [3:0] $end
$var wire 4 C c10 [3:0] $end
$var wire 1 D reset_n $end
$var wire 1 4 clock $end
$var wire 7 E binary_c [6:0] $end
$var reg 4 F hd1 [3:0] $end
$var reg 4 G hd10 [3:0] $end
$var reg 4 H hm [3:0] $end
$upscope $end
$scope module H0 $end
$var wire 4 I val [3:0] $end
$var reg 8 J seg [7:0] $end
$var reg 8 K seg1 [7:0] $end
$upscope $end
$scope module H1 $end
$var wire 4 L val [3:0] $end
$var reg 8 M seg [7:0] $end
$var reg 8 N seg1 [7:0] $end
$upscope $end
$scope module H2 $end
$var wire 4 O val [3:0] $end
$var reg 8 P seg [7:0] $end
$var reg 8 Q seg1 [7:0] $end
$upscope $end
$scope module H4 $end
$var wire 4 R val [3:0] $end
$var reg 8 S seg [7:0] $end
$var reg 8 T seg1 [7:0] $end
$upscope $end
$scope module H5 $end
$var wire 4 U val [3:0] $end
$var reg 8 V seg [7:0] $end
$var reg 8 W seg1 [7:0] $end
$upscope $end
$scope module U0 $end
$var wire 1 ( clock_in $end
$var wire 32 X divide_by [31:0] $end
$var wire 1 Y reset_n $end
$var reg 23 Z clock_divider [22:0] $end
$var reg 1 4 clock_out $end
$upscope $end
$upscope $end
$upscope $end
$enddefinitions $end
#0
$dumpvars
b0 Z
1Y
b1 X
bx W
b11111111 V
b1111 U
bx T
b11111001 S
b1 R
bx Q
b11111001 P
b1 O
bx N
b11000000 M
b0 L
bx K
b11111001 J
b1 I
b1 H
b0 G
b1 F
b1 E
1D
b0 C
b1 B
0A
b1111 @
b0 ?
b1 >
1=
0<
b1 ;
b11111001 :
b11000000 9
b11111001 8
b11111001 7
b11111111 6
b0 5
04
b1 3
b0 2
b1 1
b0 0
b1 /
b1111 .
b0 -
b1 ,
b0 +
b1 *
b0 )
0(
b11111001 '
b11000000 &
b11111001 %
b11111001 $
b11111111 #
b0 "
bz !
$end
#100
14
b1 )
1(
#200
b10 )
0(
#300
b10100100 $
b10100100 7
b10100100 S
b1 "
b1 5
1<
b10 E
b10 3
b10 >
b10 B
b10 R
04
b11 )
1(
#400
b100 )
0(
#500
14
b101 )
1(
#600
b110 )
0(
#700
b10110000 $
b10110000 7
b10110000 S
b10100100 '
b10100100 :
b10100100 J
b0 "
b0 5
0<
b11 E
b11 3
b11 >
b11 B
b11 R
b10 1
b10 F
b10 I
04
b111 )
1(
#800
b1000 )
0(
#900
14
b1001 )
1(
#1000
b1010 )
0(
#1100
b10011001 $
b10011001 7
b10011001 S
b10110000 '
b10110000 :
b10110000 J
b1 "
b1 5
1<
b100 E
b100 3
b100 >
b100 B
b100 R
b11 1
b11 F
b11 I
04
b1011 )
1(
#1200
b1100 )
0(
#1300
14
b1101 )
1(
#1400
b1110 )
0(
#1500
b10010010 $
b10010010 7
b10010010 S
b10011001 '
b10011001 :
b10011001 J
b0 "
b0 5
0<
b101 E
b101 3
b101 >
b101 B
b101 R
b100 1
b100 F
b100 I
04
b1111 )
1(
#1600
b10000 )
0(
#1700
14
b10001 )
1(
#1800
b10010 )
0(
#1900
b10000010 $
b10000010 7
b10000010 S
b10010010 '
b10010010 :
b10010010 J
b1 "
b1 5
1<
b110 E
b110 3
b110 >
b110 B
b110 R
b101 1
b101 F
b101 I
04
b10011 )
1(
#2000
b10100 )
0(
#2100
14
b10101 )
1(
#2200
b10110 )
0(
#2300
b11111000 $
b11111000 7
b11111000 S
b10000010 '
b10000010 :
b10000010 J
b0 "
b0 5
0<
b111 E
b111 3
b111 >
b111 B
b111 R
b110 1
b110 F
b110 I
04
b10111 )
1(
#2400
b11000 )
0(
#2500
14
b11001 )
1(
#2600
b11010 )
0(
#2700
b10000000 $
b10000000 7
b10000000 S
b11111000 '
b11111000 :
b11111000 J
b1 "
b1 5
1<
b1000 E
b1000 3
b1000 >
b1000 B
b1000 R
b111 1
b111 F
b111 I
04
b11011 )
1(
#2800
b11100 )
0(
#2900
14
b11101 )
1(
#3000
b11110 )
0(
#3100
b10011000 $
b10011000 7
b10011000 S
b10000000 '
b10000000 :
b10000000 J
b0 "
b0 5
0<
b1001 E
b1001 3
b1001 >
b1001 B
b1001 R
b1000 1
b1000 F
b1000 I
04
b11111 )
1(
#3200
b100000 )
0(
#3300
14
b100001 )
1(
#3400
b100010 )
0(
#3500
b11111001 #
b11111001 6
b11111001 V
b11000000 $
b11000000 7
b11000000 S
b10011000 '
b10011000 :
b10011000 J
b1 "
b1 5
1<
b1 .
b1 @
b1 U
b1 2
b1 ?
b1 C
b1010 E
b0 3
b0 >
b0 B
b0 R
b1001 1
b1001 F
b1001 I
04
b100011 )
1(
#3600
b100100 )
0(
#3700
14
b100101 )
1(
#3800
b100110 )
0(
#3900
b11111001 $
b11111001 7
b11111001 S
b11111001 &
b11111001 9
b11111001 M
b11000000 '
b11000000 :
b11000000 J
b0 "
b0 5
0<
b1011 E
b1 3
b1 >
b1 B
b1 R
b1 0
b1 G
b1 L
b0 1
b0 F
b0 I
04
b100111 )
1(
#4000
b101000 )
0(
#4100
14
b101001 )
1(
#4200
b101010 )
0(
#4300
b10100100 $
b10100100 7
b10100100 S
b11111001 '
b11111001 :
b11111001 J
b1 "
b1 5
1<
b1100 E
b10 3
b10 >
b10 B
b10 R
b1 1
b1 F
b1 I
04
b101011 )
1(
#4400
b101100 )
0(
#4500
14
b101101 )
1(
#4600
b101110 )
0(
#4700
b10110000 $
b10110000 7
b10110000 S
b10100100 '
b10100100 :
b10100100 J
b0 "
b0 5
0<
b1101 E
b11 3
b11 >
b11 B
b11 R
b10 1
b10 F
b10 I
04
b101111 )
1(
#4800
b110000 )
0(
#4900
14
b110001 )
1(
#5000
b110010 )
0(
#5100
b10011001 $
b10011001 7
b10011001 S
b10110000 '
b10110000 :
b10110000 J
b1 "
b1 5
1<
b1110 E
b100 3
b100 >
b100 B
b100 R
b11 1
b11 F
b11 I
04
b110011 )
1(
#5200
b110100 )
0(
#5300
14
b110101 )
1(
#5400
b110110 )
0(
#5500
b10010010 $
b10010010 7
b10010010 S
b10011001 '
b10011001 :
b10011001 J
b0 "
b0 5
0<
b1111 E
b101 3
b101 >
b101 B
b101 R
b100 1
b100 F
b100 I
04
b110111 )
1(
#5600
b111000 )
0(
#5700
14
b111001 )
1(
#5800
b111010 )
0(
#5900
b10000010 $
b10000010 7
b10000010 S
b10010010 '
b10010010 :
b10010010 J
b1 "
b1 5
1<
b10000 E
b110 3
b110 >
b110 B
b110 R
b101 1
b101 F
b101 I
04
b111011 )
1(
#6000
b111100 )
0(
#6100
14
b111101 )
1(
#6200
b111110 )
0(
#6300
b11111000 $
b11111000 7
b11111000 S
b10000010 '
b10000010 :
b10000010 J
b0 "
b0 5
0<
b10001 E
b111 3
b111 >
b111 B
b111 R
b110 1
b110 F
b110 I
04
b111111 )
1(
#6400
b1000000 )
0(
#6500
14
b1000001 )
1(
#6600
b1000010 )
0(
#6700
b10000000 $
b10000000 7
b10000000 S
b11111000 '
b11111000 :
b11111000 J
b1 "
b1 5
1<
b10010 E
b1000 3
b1000 >
b1000 B
b1000 R
b111 1
b111 F
b111 I
04
b1000011 )
1(
#6800
b1000100 )
0(
#6900
14
b1000101 )
1(
#7000
b1000110 )
0(
#7100
b10011000 $
b10011000 7
b10011000 S
b10000000 '
b10000000 :
b10000000 J
b0 "
b0 5
0<
b10011 E
b1001 3
b1001 >
b1001 B
b1001 R
b1000 1
b1000 F
b1000 I
04
b1000111 )
1(
#7200
b1001000 )
0(
#7300
14
b1001001 )
1(
#7400
b1001010 )
0(
#7500
b10100100 #
b10100100 6
b10100100 V
b11000000 $
b11000000 7
b11000000 S
b10011000 '
b10011000 :
b10011000 J
b1 "
b1 5
1<
b10 .
b10 @
b10 U
b10 2
b10 ?
b10 C
b10100 E
b0 3
b0 >
b0 B
b0 R
b1001 1
b1001 F
b1001 I
04
b1001011 )
1(
#7600
b1001100 )
0(
#7700
14
b1001101 )
1(
#7800
b1001110 )
0(
#7900
b11111001 $
b11111001 7
b11111001 S
b10100100 &
b10100100 9
b10100100 M
b11000000 '
b11000000 :
b11000000 J
b0 "
b0 5
0<
b10101 E
b1 3
b1 >
b1 B
b1 R
b10 0
b10 G
b10 L
b0 1
b0 F
b0 I
04
b1001111 )
1(
#8000
b1010000 )
0(
#8100
14
b1010001 )
1(
#8200
b1010010 )
0(
#8300
b10100100 $
b10100100 7
b10100100 S
b11111001 '
b11111001 :
b11111001 J
b1 "
b1 5
1<
b10110 E
b10 3
b10 >
b10 B
b10 R
b1 1
b1 F
b1 I
04
b1010011 )
1(
#8400
b1010100 )
0(
#8500
14
b1010101 )
1(
#8600
b1010110 )
0(
#8700
b10110000 $
b10110000 7
b10110000 S
b10100100 '
b10100100 :
b10100100 J
b0 "
b0 5
0<
b10111 E
b11 3
b11 >
b11 B
b11 R
b10 1
b10 F
b10 I
04
b1010111 )
1(
#8800
b1011000 )
0(
#8900
14
b1011001 )
1(
#9000
b1011010 )
0(
#9100
b10011001 $
b10011001 7
b10011001 S
b10110000 '
b10110000 :
b10110000 J
b1 "
b1 5
1<
b11000 E
b100 3
b100 >
b100 B
b100 R
b11 1
b11 F
b11 I
04
b1011011 )
1(
#9200
b1011100 )
0(
#9300
14
b1011101 )
1(
#9400
b1011110 )
0(
#9500
b10010010 $
b10010010 7
b10010010 S
b10011001 '
b10011001 :
b10011001 J
b0 "
b0 5
0<
b11001 E
b101 3
b101 >
b101 B
b101 R
b100 1
b100 F
b100 I
04
b1011111 )
1(
#9600
b1100000 )
0(
#9700
14
b1100001 )
1(
#9800
b1100010 )
0(
#9900
b10000010 $
b10000010 7
b10000010 S
b10010010 '
b10010010 :
b10010010 J
b1 "
b1 5
1<
b11010 E
b110 3
b110 >
b110 B
b110 R
b101 1
b101 F
b101 I
04
b1100011 )
1(
#10000
b1100100 )
0(
#10100
14
b1100101 )
1(
#10200
b1100110 )
0(
#10300
b11111000 $
b11111000 7
b11111000 S
b10000010 '
b10000010 :
b10000010 J
b0 "
b0 5
0<
b11011 E
b111 3
b111 >
b111 B
b111 R
b110 1
b110 F
b110 I
04
b1100111 )
1(
#10400
b1101000 )
0(
#10500
14
b1101001 )
1(
#10600
b1101010 )
0(
#10700
b10000000 $
b10000000 7
b10000000 S
b11111000 '
b11111000 :
b11111000 J
b1 "
b1 5
1<
b11100 E
b1000 3
b1000 >
b1000 B
b1000 R
b111 1
b111 F
b111 I
04
b1101011 )
1(
#10800
b1101100 )
0(
#10900
14
b1101101 )
1(
#11000
b1101110 )
0(
#11100
b10011000 $
b10011000 7
b10011000 S
b10000000 '
b10000000 :
b10000000 J
b0 "
b0 5
0<
b11101 E
b1001 3
b1001 >
b1001 B
b1001 R
b1000 1
b1000 F
b1000 I
04
b1101111 )
1(
#11200
b1110000 )
0(
#11300
14
b1110001 )
1(
#11400
b1110010 )
0(
#11500
b10110000 #
b10110000 6
b10110000 V
b11000000 $
b11000000 7
b11000000 S
b10011000 '
b10011000 :
b10011000 J
b1 "
b1 5
1<
b11 .
b11 @
b11 U
b11 2
b11 ?
b11 C
b11110 E
b0 3
b0 >
b0 B
b0 R
b1001 1
b1001 F
b1001 I
04
b1110011 )
1(
#11600
b1110100 )
0(
#11700
14
b1110101 )
1(
#11800
b1110110 )
0(
#11900
b11111001 $
b11111001 7
b11111001 S
b10110000 &
b10110000 9
b10110000 M
b11000000 '
b11000000 :
b11000000 J
b0 "
b0 5
0<
b11111 E
b1 3
b1 >
b1 B
b1 R
b11 0
b11 G
b11 L
b0 1
b0 F
b0 I
04
b1110111 )
1(
#12000
b1111000 )
0(
#12100
14
b1111001 )
1(
#12200
b1111010 )
0(
#12300
b10100100 $
b10100100 7
b10100100 S
b10100100 %
b10100100 8
b10100100 P
b11111001 '
b11111001 :
b11111001 J
b1 "
b1 5
1<
b100000 E
b10 3
b10 >
b10 B
b10 R
b10 /
b10 H
b10 O
b1 1
b1 F
b1 I
04
b1111011 )
1(
#12400
b1111100 )
0(
#12500
14
b1111101 )
1(
#12600
b1111110 )
0(
#12700
b10110000 $
b10110000 7
b10110000 S
b11000000 &
b11000000 9
b11000000 M
b0 "
b0 5
0<
b100001 E
b11 3
b11 >
b11 B
b11 R
b0 0
b0 G
b0 L
04
b1111111 )
1(
#12800
b10000000 )
0(
#12900
14
b10000001 )
1(
#13000
b10000010 )
0(
#13100
b10011001 $
b10011001 7
b10011001 S
b10100100 '
b10100100 :
b10100100 J
b1 "
b1 5
1<
b100010 E
b100 3
b100 >
b100 B
b100 R
b10 1
b10 F
b10 I
04
b10000011 )
1(
#13200
b10000100 )
0(
#13300
14
b10000101 )
1(
#13400
b10000110 )
0(
#13500
b10010010 $
b10010010 7
b10010010 S
b10110000 '
b10110000 :
b10110000 J
b0 "
b0 5
0<
b100011 E
b101 3
b101 >
b101 B
b101 R
b11 1
b11 F
b11 I
04
b10000111 )
1(
#13600
b10001000 )
0(
#13700
14
b10001001 )
1(
#13800
b10001010 )
0(
#13900
b10000010 $
b10000010 7
b10000010 S
b10011001 '
b10011001 :
b10011001 J
b1 "
b1 5
1<
b100100 E
b110 3
b110 >
b110 B
b110 R
b100 1
b100 F
b100 I
04
b10001011 )
1(
#14000
b10001100 )
0(
#14100
14
b10001101 )
1(
#14200
b10001110 )
0(
#14300
b11111000 $
b11111000 7
b11111000 S
b10010010 '
b10010010 :
b10010010 J
b0 "
b0 5
0<
b100101 E
b111 3
b111 >
b111 B
b111 R
b101 1
b101 F
b101 I
04
b10001111 )
1(
#14400
b10010000 )
0(
#14500
14
b10010001 )
1(
#14600
b10010010 )
0(
#14700
b10000000 $
b10000000 7
b10000000 S
b10000010 '
b10000010 :
b10000010 J
b1 "
b1 5
1<
b100110 E
b1000 3
b1000 >
b1000 B
b1000 R
b110 1
b110 F
b110 I
04
b10010011 )
1(
#14800
b10010100 )
0(
#14900
14
b10010101 )
1(
#15000
b10010110 )
0(
#15100
b10011000 $
b10011000 7
b10011000 S
b11111000 '
b11111000 :
b11111000 J
b0 "
b0 5
0<
b100111 E
b1001 3
b1001 >
b1001 B
b1001 R
b111 1
b111 F
b111 I
04
b10010111 )
1(
#15200
b10011000 )
0(
#15300
14
b10011001 )
1(
#15400
b10011010 )
0(
#15500
b10011001 #
b10011001 6
b10011001 V
b11000000 $
b11000000 7
b11000000 S
b10000000 '
b10000000 :
b10000000 J
b1 "
b1 5
1<
b100 .
b100 @
b100 U
b100 2
b100 ?
b100 C
b101000 E
b0 3
b0 >
b0 B
b0 R
b1000 1
b1000 F
b1000 I
04
b10011011 )
1(
#15600
b10011100 )
0(
#15700
14
b10011101 )
1(
#15800
b10011110 )
0(
#15900
b11111001 $
b11111001 7
b11111001 S
b10011000 '
b10011000 :
b10011000 J
b0 "
b0 5
0<
b101001 E
b1 3
b1 >
b1 B
b1 R
b1001 1
b1001 F
b1001 I
04
b10011111 )
1(
#16000
b10100000 )
0(
#16100
14
b10100001 )
1(
#16200
b10100010 )
0(
#16300
b10100100 $
b10100100 7
b10100100 S
b11111001 &
b11111001 9
b11111001 M
b11000000 '
b11000000 :
b11000000 J
b1 "
b1 5
1<
b101010 E
b10 3
b10 >
b10 B
b10 R
b1 0
b1 G
b1 L
b0 1
b0 F
b0 I
04
b10100011 )
1(
#16400
b10100100 )
0(
#16500
14
b10100101 )
1(
#16600
b10100110 )
0(
#16700
b10110000 $
b10110000 7
b10110000 S
b11111001 '
b11111001 :
b11111001 J
b0 "
b0 5
0<
b101011 E
b11 3
b11 >
b11 B
b11 R
b1 1
b1 F
b1 I
04
b10100111 )
1(
#16800
b10101000 )
0(
#16900
14
b10101001 )
1(
#17000
b10101010 )
0(
#17100
b10011001 $
b10011001 7
b10011001 S
b10100100 '
b10100100 :
b10100100 J
b1 "
b1 5
1<
b101100 E
b100 3
b100 >
b100 B
b100 R
b10 1
b10 F
b10 I
04
b10101011 )
1(
#17200
b10101100 )
0(
#17300
14
b10101101 )
1(
#17400
b10101110 )
0(
#17500
b10010010 $
b10010010 7
b10010010 S
b10110000 '
b10110000 :
b10110000 J
b0 "
b0 5
0<
b101101 E
b101 3
b101 >
b101 B
b101 R
b11 1
b11 F
b11 I
04
b10101111 )
1(
#17600
b10110000 )
0(
#17700
14
b10110001 )
1(
#17800
b10110010 )
0(
#17900
b10000010 $
b10000010 7
b10000010 S
b10011001 '
b10011001 :
b10011001 J
b1 "
b1 5
1<
b101110 E
b110 3
b110 >
b110 B
b110 R
b100 1
b100 F
b100 I
04
b10110011 )
1(
#18000
b10110100 )
0(
#18100
14
b10110101 )
1(
#18200
b10110110 )
0(
#18300
b11111000 $
b11111000 7
b11111000 S
b10010010 '
b10010010 :
b10010010 J
b0 "
b0 5
0<
b101111 E
b111 3
b111 >
b111 B
b111 R
b101 1
b101 F
b101 I
04
b10110111 )
1(
#18400
b10111000 )
0(
#18500
14
b10111001 )
1(
#18600
b10111010 )
0(
#18700
b10000000 $
b10000000 7
b10000000 S
b10000010 '
b10000010 :
b10000010 J
b1 "
b1 5
1<
b110000 E
b1000 3
b1000 >
b1000 B
b1000 R
b110 1
b110 F
b110 I
04
b10111011 )
1(
#18800
b10111100 )
0(
#18900
14
b10111101 )
1(
#19000
b10111110 )
0(
#19100
b10011000 $
b10011000 7
b10011000 S
b11111000 '
b11111000 :
b11111000 J
b0 "
b0 5
0<
b110001 E
b1001 3
b1001 >
b1001 B
b1001 R
b111 1
b111 F
b111 I
04
b10111111 )
1(
#19200
b11000000 )
0(
#19300
14
b11000001 )
1(
#19400
b11000010 )
0(
#19500
b10010010 #
b10010010 6
b10010010 V
b11000000 $
b11000000 7
b11000000 S
b10000000 '
b10000000 :
b10000000 J
b1 "
b1 5
1<
b101 .
b101 @
b101 U
b101 2
b101 ?
b101 C
b110010 E
b0 3
b0 >
b0 B
b0 R
b1000 1
b1000 F
b1000 I
04
b11000011 )
1(
#19600
b11000100 )
0(
#19700
14
b11000101 )
1(
#19800
b11000110 )
0(
#19900
b11111001 $
b11111001 7
b11111001 S
b10011000 '
b10011000 :
b10011000 J
b0 "
b0 5
0<
b110011 E
b1 3
b1 >
b1 B
b1 R
b1001 1
b1001 F
b1001 I
04
b11000111 )
1(
#20000
b11001000 )
0(
#20100
14
b11001001 )
1(
#20200
b11001010 )
0(
#20300
b10100100 $
b10100100 7
b10100100 S
b10100100 &
b10100100 9
b10100100 M
b11000000 '
b11000000 :
b11000000 J
b1 "
b1 5
1<
b110100 E
b10 3
b10 >
b10 B
b10 R
b10 0
b10 G
b10 L
b0 1
b0 F
b0 I
04
b11001011 )
1(
#20400
b11001100 )
0(
#20500
14
b11001101 )
1(
#20600
b11001110 )
0(
#20700
b10110000 $
b10110000 7
b10110000 S
b11111001 '
b11111001 :
b11111001 J
b0 "
b0 5
0<
b110101 E
b11 3
b11 >
b11 B
b11 R
b1 1
b1 F
b1 I
04
b11001111 )
1(
#20800
b11010000 )
0(
#20900
14
b11010001 )
1(
#21000
b11010010 )
0(
#21100
b10011001 $
b10011001 7
b10011001 S
b10100100 '
b10100100 :
b10100100 J
b1 "
b1 5
1<
b110110 E
b100 3
b100 >
b100 B
b100 R
b10 1
b10 F
b10 I
04
b11010011 )
1(
#21200
b11010100 )
0(
#21300
14
b11010101 )
1(
#21400
b11010110 )
0(
#21500
b10010010 $
b10010010 7
b10010010 S
b10110000 '
b10110000 :
b10110000 J
b0 "
b0 5
0<
b110111 E
b101 3
b101 >
b101 B
b101 R
b11 1
b11 F
b11 I
04
b11010111 )
1(
#21600
b11011000 )
0(
#21700
14
b11011001 )
1(
#21800
b11011010 )
0(
#21900
b10000010 $
b10000010 7
b10000010 S
b10011001 '
b10011001 :
b10011001 J
b1 "
b1 5
1<
b111000 E
b110 3
b110 >
b110 B
b110 R
b100 1
b100 F
b100 I
04
b11011011 )
1(
#22000
b11011100 )
0(
#22100
14
b11011101 )
1(
#22200
b11011110 )
0(
#22300
b11111000 $
b11111000 7
b11111000 S
b10010010 '
b10010010 :
b10010010 J
b0 "
b0 5
0<
b111001 E
b111 3
b111 >
b111 B
b111 R
b101 1
b101 F
b101 I
04
b11011111 )
1(
#22400
b11100000 )
0(
#22500
14
b11100001 )
1(
#22600
b11100010 )
0(
#22700
b10000000 $
b10000000 7
b10000000 S
b10000010 '
b10000010 :
b10000010 J
b1 "
b1 5
1<
b111010 E
b1000 3
b1000 >
b1000 B
b1000 R
b110 1
b110 F
b110 I
04
b11100011 )
1(
#22800
b11100100 )
0(
#22900
14
b11100101 )
1(
#23000
b11100110 )
0(
#23100
b10011000 $
b10011000 7
b10011000 S
b11111000 '
b11111000 :
b11111000 J
b0 "
b0 5
0<
b111011 E
b1001 3
b1001 >
b1001 B
b1001 R
b111 1
b111 F
b111 I
04
b11100111 )
1(
#23200
b11101000 )
0(
#23300
14
b11101001 )
1(
#23400
b11101010 )
0(
#23500
b10000010 #
b10000010 6
b10000010 V
b11000000 $
b11000000 7
b11000000 S
b1 "
b1 5
1<
b110 .
b110 @
b110 U
b110 2
b110 ?
b110 C
b111100 E
b0 3
b0 >
b0 B
b0 R
04
b11101011 )
1(
#23600
b11101100 )
0(
#23700
14
b11101101 )
1(
#23800
b11101110 )
0(
#23900
b11111001 $
b11111001 7
b11111001 S
b0 "
b0 5
0<
b111101 E
b1 3
b1 >
b1 B
b1 R
04
b11101111 )
1(
#24000
b11110000 )
0(
#24100
14
b11110001 )
1(
#24200
b11110010 )
0(
#24300
b10100100 $
b10100100 7
b10100100 S
b1 "
b1 5
1<
b111110 E
b10 3
b10 >
b10 B
b10 R
04
b11110011 )
1(
#24400
b11110100 )
0(
#24500
14
b11110101 )
1(
#24600
b11110110 )
0(
#24700
b10110000 $
b10110000 7
b10110000 S
b0 "
b0 5
0<
b111111 E
b11 3
b11 >
b11 B
b11 R
04
b11110111 )
1(
#24800
b11111000 )
0(
#24900
14
b11111001 )
1(
#25000
b11111010 )
0(
