Project 2/sevenSeg.v
// ALTERED SEVEN SEG so that there is blanking and no letters. See project 1 for real SevenSeg module
module sevenSeg (input [3:0] val, output reg [7:0] seg, output reg [7:0] seg1);

always @(val)
  begin
    case(val[3:0])
      4'b0000 : seg = 8'b11000000;
      4'b0001 : seg = 8'b11111001;
      4'b0010 : seg = 8'b10100100;
      4'b0011 : seg = 8'b10110000;
      4'b0100 : seg = 8'b10011001;
      4'b0101 : seg = 8'b10010010;
      4'b0110 : seg = 8'b10000010;
      4'b0111 : seg = 8'b11111000;
      4'b1000 : seg = 8'b10000000;
      4'b1001 : seg = 8'b10011000;

      //Code to blank the display
      4'b1111 : seg = 8'b11111111;
      default : seg = 8'b11111111;
    endcase
  end
endmodule

Project 2/clockDivider.v
module clockDivider(clock_in, reset_n, clock_out);
input clock_in;
input reset_n;
output reg clock_out;

reg [22:0] clock_divider = 0;
parameter divide_by = 2500000;
initial begin
  clock_out = 0;
  clock_divider = 0;
end
always @(posedge clock_in or negedge reset_n)
  begin
    if (~reset_n)
      begin
        clock_out = 0;
        clock_divider = 0;
      end
    else
      begin
        if(clock_divider != divide_by - 1)
          clock_divider <= clock_divider + 1;
        else
          begin
            clock_divider <= 0;
            clock_out <= ~clock_out;
          end
      end
  end
endmodule

Project 2/top.v
module top (ADC_CLK_10, KEY, HEX0, HEX1, HEX2, HEX4, HEX5, LEDR);

input ADC_CLK_10;
input [0:0] KEY;

output [7:0] HEX0;
output [7:0] HEX1;
output [7:0] HEX2;
output [7:0] HEX4;
output [7:0] HEX5;
output [9:0] LEDR;

wire clock;
reg clock_reset;

clockDivider U0 (.clock_in(ADC_CLK_10), .reset_n(KEY[0]), .clock_out(clock));

reg [3:0] counter1;
reg [3:0] counter10;

reg [3:0] segCounter10;

sevenSeg H4 (.val(counter1), .seg(HEX4));
sevenSeg H5 (.val(counter10), .seg(HEX5));

reg ledValue;

assign LEDR[9:1] = 9'b0_0000_0000;
assign LEDR[0] = ledValue;

initial begin
    counter1 = 1;
    counter10 = 0;
    segCounter10 = 0;
    clock_reset = 1;
end

always @ (posedge clock or negedge KEY[0])
    begin
        /*if (counter10 == 4'b0000)
        begin
            segCounter10 <= 4'b1111;
        end
        else
        begin
            segCounter10 <= counter10;
        end */
       if (~KEY[0])
       begin
            counter1 <= 1;
            counter10 <= 0;
        end
        else
        begin
            ledValue <= ~ledValue;
            if (counter1 != 4'b1001)
            begin
                counter1 <= counter1 + 1;
            end
            else
            begin
                if (counter10 != 4'b1001)
                begin
                    counter1 <= 0;
                    counter10 <= counter10 + 1;
                end
                else
                begin
                    counter1 <= 1;
                    counter10 <= 0;
                end
            end
        end
    end


endmodule

Project 2/tbtop.v
`timescale 1 ns / 100 ps

module tbtop();

reg [9:0] testSW;
reg  testKEY;
reg clock;
reg [15:0] counter;
wire [9:0] testLED;
wire [7:0] testHEX0;
wire [7:0] testHEX1;
wire [7:0] testHEX2;
wire [7:0] testHEX3;
wire [7:0] testHEX4;
wire [7:0] testHEX5;

top DUT(.KEY(testKEY), .ADC_CLK_10(clock), .LEDR(testLED),.HEX0(testHEX0),.HEX1(testHEX1),.HEX2(testHEX2),.HEX4(testHEX4),.HEX5(testHEX5));

// Begin stimulating inputs:
initial begin
  $dumpfile("test.vcd");
  $dumpvars;
  $display($time, "Starting simulation");

  //Initialize inputs:
  testSW = 10'b0000000000;
  testKEY = 1;
  clock = 1'b0;
  counter = 0;
  while(counter < 16'b1111111111111111) begin
    #10 clock = ~clock;
    counter = counter + 1;
  end
  // End testing
  #10 $finish;
end

// Monitor inputs and outputs
initial
  begin
    $monitor($time, "testSW = %b, testKEY = %b, clock = %b, testLED = %b, testHEX0 = %b, testHEX1 = %b, testHEX2 = %b, testHEX3 = %b, testHEX4 = %b, testHEX5 = %b",
           testSW, testKEY, testLED, clock, testHEX0, testHEX1, testHEX2, testHEX3, testHEX4, testHEX5);
  end
endmodule

Project 2/test.vcd
$date
	Thu Feb 27 16:30:08 2020
$end
$version
	Icarus Verilog
$end
$timescale
	100ps
$end
$scope module tbtop $end
$var wire 8 ! testHEX0 [7:0] $end
$var wire 8 " testHEX1 [7:0] $end
$var wire 8 # testHEX2 [7:0] $end
$var wire 8 $ testHEX3 [7:0] $end
$var wire 10 % testLED [9:0] $end
$var wire 8 & testHEX5 [7:0] $end
$var wire 8 ' testHEX4 [7:0] $end
$var reg 1 ( clock $end
$var reg 16 ) counter [15:0] $end
$var reg 1 * testKEY $end
$var reg 10 + testSW [9:0] $end
$scope module DUT $end
$var wire 1 ( ADC_CLK_10 $end
$var wire 8 , HEX0 [7:0] $end
$var wire 8 - HEX1 [7:0] $end
$var wire 8 . HEX2 [7:0] $end
$var wire 1 * KEY $end
$var wire 1 / clock $end
$var wire 10 0 LEDR [9:0] $end
$var wire 8 1 HEX5 [7:0] $end
$var wire 8 2 HEX4 [7:0] $end
$var reg 1 3 clock_reset $end
$var reg 4 4 counter1 [3:0] $end
$var reg 4 5 counter10 [3:0] $end
$var reg 1 6 ledValue $end
$var reg 4 7 segCounter10 [3:0] $end
$scope module H4 $end
$var wire 4 8 val [3:0] $end
$var reg 8 9 seg [7:0] $end
$var reg 8 : seg1 [7:0] $end
$upscope $end
$scope module H5 $end
$var wire 4 ; val [3:0] $end
$var reg 8 < seg [7:0] $end
$var reg 8 = seg1 [7:0] $end
$upscope $end
$scope module U0 $end
$var wire 1 ( clock_in $end
$var wire 1 * reset_n $end
$var reg 23 > clock_divider [22:0] $end
$var reg 1 / clock_out $end
$upscope $end
$upscope $end
$upscope $end
$enddefinitions $end
#0
$dumpvars
b0 >
bx =
b11000000 <
b0 ;
bx :
b11111001 9
b1 8
b0 7
x6
b0 5
b1 4
13
b11111001 2
b11000000 1
b0x 0
0/
bz .
bz -
bz ,
b0 +
1*
b0 )
0(
b11111001 '
b11000000 &
b0x %
bz $
bz #
bz "
bz !
$end
#100
b1 >
b1 )
1(
#200
b10 )
0(
#300
b10 >
b11 )
1(
#400
b100 )
0(
#500
b11 >
b101 )
1(
#600
b110 )
0(
#700
b100 >
b111 )
1(
#800
b1000 )
0(
#900
b101 >
b1001 )
1(
#1000
b1010 )
0(
#1100
b110 >
b1011 )
1(
#1200
b1100 )
0(
#1300
b111 >
b1101 )
1(
#1400
b1110 )
0(
#1500
b1000 >
b1111 )
1(
#1600
b10000 )
0(
#1700
b1001 >
b10001 )
1(
#1800
b10010 )
0(
#1900
b1010 >
b10011 )
1(
#2000
b10100 )
0(
#2100
b1011 >
b10101 )
1(
#2200
b10110 )
0(
#2300
b1100 >
b10111 )
1(
#2400
b11000 )
0(
#2500
b1101 >
b11001 )
1(
#2600
b11010 )
0(
#2700
b1110 >
b11011 )
1(
#2800
b11100 )
0(
#2900
b1111 >
b11101 )
1(
#3000
b11110 )
0(
#3100
b10000 >
b11111 )
1(
#3200
b100000 )
0(
#3300
b10001 >
b100001 )
1(
#3400
b100010 )
0(
#3500
b10010 >
b100011 )
1(
#3600
b100100 )
0(
#3700
b10011 >
b100101 )
1(
#3800
b100110 )
0(
#3900
b10100 >
b100111 )
1(
#4000
b101000 )
0(
#4100
b10101 >
b101001 )
1(
#4200
b101010 )
0(
#4300
b10110 >
b101011 )
1(
#4400
b101100 )
0(
#4500
b10111 >
b101101 )
1(
#4600
b101110 )
0(
#4700
b11000 >
b101111 )
1(
#4800
b110000 )
0(
#4900
b11001 >
b110001 )
1(
#5000
b110010 )
0(
#5100
b11010 >
b110011 )
1(
#5200
b110100 )
0(
#5300
b11011 >
b110101 )
1(
#5400
b110110 )
0(
#5500
b11100 >
b110111 )
1(
#5600
b111000 )
0(
#5700
b11101 >
b111001 )
1(
#5800
b111010 )
0(
#5900
b11110 >
b111011 )
1(
#6000
b111100 )
0(
#6100
b11111 >
b111101 )
1(
#6200
b111110 )
0(
#6300
b100000 >
b111111 )
1(
#6400
b1000000 )
0(
#6500
b100001 >
b1000001 )
1(
#6600
b1000010 )
0(
#6700
b100010 >
b1000011 )
1(
#6800
b1000100 )
0(
#6900
b100011 >
b1000101 )
1(
#7000
b1000110 )
0(
#7100
b100100 >
b1000111 )
1(
#7200
b1001000 )
0(
#7300
b100101 >
b1001001 )
1(
#7400
b1001010 )
0(
#7500
b100110 >
b1001011 )
1(
#7600
b1001100 )
0(
#7700
b100111 >
b1001101 )
1(
#7800
b1001110 )
0(
#7900
b101000 >
b1001111 )
1(
#8000
b1010000 )
0(
#8100
b101001 >
b1010001 )
1(
#8200
b1010010 )
0(
#8300
b101010 >
b1010011 )
1(
#8400
b1010100 )
0(
#8500
b101011 >
b1010101 )
1(
#8600
b1010110 )
0(
#8700
b101100 >
b1010111 )
1(
#8800
b1011000 )
0(
#8900
b101101 >
b1011001 )
1(
#9000
b1011010 )
0(
#9100
b101110 >
b1011011 )
1(
#9200
b1011100 )
0(
#9300
b101111 >
b1011101 )
1(
#9400
b1011110 )
0(
#9500
b110000 >
b1011111 )
1(
#9600
b1100000 )
0(
#9700
b110001 >
b1100001 )
1(
#9800
b1100010 )
0(
#9900
b110010 >
b1100011 )
1(
#10000
b1100100 )
0(
#10100
b110011 >
b1100101 )
1(
#10200
b1100110 )
0(
#10300
b110100 >
b1100111 )
1(
#10400
b1101000 )
0(
#10500
b110101 >
b1101001 )
1(
#10600
b1101010 )
0(
#10700
b110110 >
b1101011 )
1(
#10800
b1101100 )
0(
#10900
b110111 >
b1101101 )
1(
#11000
b1101110 )
0(
#11100
b111000 >
b1101111 )
1(
#11200
b1110000 )
0(
#11300
b111001 >
b1110001 )
1(
#11400
b1110010 )
0(
#11500
b111010 >
b1110011 )
1(
#11600
b1110100 )
0(
#11700
b111011 >
b1110101 )
1(
#11800
b1110110 )
0(
#11900
b111100 >
b1110111 )
1(
#12000
b1111000 )
0(
#12100
b111101 >
b1111001 )
1(
#12200
b1111010 )
0(
#12300
b111110 >
b1111011 )
1(
#12400
b1111100 )
0(
#12500
b111111 >
b1111101 )
1(
#12600
b1111110 )
0(
#12700
b1000000 >
b1111111 )
1(
#12800
b10000000 )
0(
#12900
b1000001 >
b10000001 )
1(
#13000
b10000010 )
0(
#13100
b1000010 >
b10000011 )
1(
#13200
b10000100 )
0(
#13300
b1000011 >
b10000101 )
1(
#13400
b10000110 )
0(
#13500
b1000100 >
b10000111 )
1(
#13600
b10001000 )
0(
#13700
b1000101 >
b10001001 )
1(
#13800
b10001010 )
0(
#13900
b1000110 >
b10001011 )
1(
#14000
b10001100 )
0(
#14100
b1000111 >
b10001101 )
1(
#14200
b10001110 )
0(
#14300
b1001000 >
b10001111 )
1(
#14400
b10010000 )
0(
#14500
b1001001 >
b10010001 )
1(
#14600
b10010010 )
0(
#14700
b1001010 >
b10010011 )
1(
#14800
b10010100 )
0(
#14900
b1001011 >
b10010101 )
1(
#15000
b10010110 )
0(
#15100
b1001100 >
b10010111 )
1(
#15200
b10011000 )
0(
#15300
b1001101 >
b10011001 )
1(
#15400
b10011010 )
0(
#15500
b1001110 >
b10011011 )
1(
#15600
b10011100 )
0(
#15700
b1001111 >
b10011101 )
1(
#15800
b10011110 )
0(
#15900
b1010000 >
b10011111 )
1(
#16000
b10100000 )
0(
#16100
b1010001 >
b10100001 )
1(
#16200
b10100010 )
0(
#16300
b1010010 >
b10100011 )
1(
#16400
b10100100 )
0(
#16500
b1010011 >
b10100101 )
1(
#16600
b10100110 )
0(
#16700
b1010100 >
b10100111 )
1(
#16800
b10101000 )
0(
#16900
b1010101 >
b10101001 )
1(
#17000
b10101010 )
0(
#17100
b1010110 >
b10101011 )
1(
#17200
b10101100 )
0(
#17300
b1010111 >
b10101101 )
1(
#17400
b10101110 )
0(
#17500
b1011000 >
b10101111 )
1(
#17600
b10110000 )
0(
#17700
b1011001 >
b10110001 )
1(
#17800
b10110010 )
0(
#17900
b1011010 >
b10110011 )
1(
#18000
b10110100 )
0(
#18100
b1011011 >
b10110101 )
1(
#18200
b10110110 )
0(
#18300
b1011100 >
b10110111 )
1(
#18400
b10111000 )
0(
#18500
b1011101 >
b10111001 )
1(
#18600
b10111010 )
0(
#18700
b1011110 >
b10111011 )
1(
#18800
b10111100 )
0(
#18900
b1011111 >
b10111101 )
1(
#19000
b10111110 )
0(
#19100
b1100000 >
b10111111 )
1(
#19200
b11000000 )
0(
#19300
b1100001 >
b11000001 )
1(
#19400
b11000010 )
0(
#19500
b1100010 >
b11000011 )
1(
#19600
b11000100 )
0(
#19700
b1100011 >
b11000101 )
1(
#19800
b11000110 )
0(
#19900
b1100100 >
b11000111 )
1(
#20000
b11001000 )
0(
#20100
b1100101 >
b11001001 )
1(
#20200
b11001010 )
0(
#20300
b1100110 >
b11001011 )
1(
#20400
b11001100 )
0(
#20500
b1100111 >
b11001101 )
1(
#20600
b11001110 )
0(
#20700
b1101000 >
b11001111 )
1(
#20800
b11010000 )
0(
#20900
b1101001 >
b11010001 )
1(
#21000
b11010010 )
0(
#21100
b1101010 >
b11010011 )
1(
#21200
b11010100 )
0(
#21300
b1101011 >
b11010101 )
1(
#21400
b11010110 )
0(
#21500
b1101100 >
b11010111 )
1(
#21600
b11011000 )
0(
#21700
b1101101 >
b11011001 )
1(
#21800
b11011010 )
0(
#21900
b1101110 >
b11011011 )
1(
#22000
b11011100 )
0(
#22100
b1101111 >
b11011101 )
1(
#22200
b11011110 )
0(
#22300
b1110000 >
b11011111 )
1(
#22400
b11100000 )
0(
#22500
b1110001 >
b11100001 )
1(
#22600
b11100010 )
0(
#22700
b1110010 >
b11100011 )
1(
#22800
b11100100 )
0(
#22900
b1110011 >
b11100101 )
1(
#23000
b11100110 )
0(
#23100
b1110100 >
b11100111 )
1(
#23200
b11101000 )
0(
#23300
b1110101 >
b11101001 )
1(
#23400
b11101010 )
0(
#23500
b1110110 >
b11101011 )
1(
#23600
b11101100 )
0(
#23700
b1110111 >
b11101101 )
1(
#23800
b11101110 )
0(
#23900
b1111000 >
b11101111 )
1(
#24000
b11110000 )
0(
#24100
b1111001 >
b11110001 )
1(
#24200
b11110010 )
0(
#24300
b1111010 >
b11110011 )
1(
#24400
b11110100 )
0(
#24500
b1111011 >
b11110101 )
1(
#24600
b11110110 )
0(
#24700
b1111100 >
b11110111 )
1(
#24800
b11111000 )
0(
#24900
b1111101 >
b11111001 )
1(
#25000
b11111010 )
0(
#25100
b1111110 >
b11111011 )
1(
#25200
b11111100 )
0(
#25300
b1111111 >
b11111101 )
1(
#25400
b11111110 )
0(
#25500
b10000000 >
b11111111 )
1(
#25600
b100000000 )
0(
#25700
b10000001 >
b100000001 )
1(
#25800
b100000010 )
0(
#25900
b10000010 >
b100000011 )
1(
#26000
b100000100 )
0(
#26100
b10000011 >
b100000101 )
1(
#26200
b100000110 )
0(
#26300
b10000100 >
b100000111 )
1(
#26400
b100001000 )
0(
#26500
b10000101 >
b100001001 )
1(
#26600
b100001010 )
0(
#26700
b10000110 >
b100001011 )
1(
#26800
b100001100 )
0(
#26900
b10000111 >
b100001101 )
1(
#27000
b100001110 )
0(
#27100
b10001000 >
b100001111 )
1(
#27200
b100010000 )
0(
#27300
b10001001 >
b100010001 )
1(
#27400
b100010010 )
0(
#27500
b10001010 >
b100010011 )
1(
#27600
b100010100 )
0(
#27700
b10001011 >
b100010101 )
1(
#27800
b100010110 )
0(
#27900
b10001100 >
b100010111 )
1(
#28000
b100011000 )
0(
#28100
b10001101 >
b100011001 )
1(
#28200
b100011010 )
0(
#28300
b10001110 >
b100011011 )
1(
#28400
b100011100 )
0(
#28500
b10001111 >
b100011101 )
1(
#28600
b100011110 )
0(
#28700
b10010000 >
b100011111 )
1(
#28800
b100100000 )
0(
#28900
b10010001 >
b100100001 )
1(
#29000
b100100010 )
0(
#29100
b10010010 >
b100100011 )
1(
#29200
b100100100 )
0(
#29300
b10010011 >
b100100101 )
1(
#29400
b100100110 )
0(
#29500
b10010100 >
b100100111 )
1(
#29600
b100101000 )
0(
#29700
b10010101 >
b100101001 )
1(
#29800
b100101010 )
0(
#29900
b10010110 >
b100101011 )
1(
#30000
b100101100 )
0(
#30100
b10010111 >
b100101101 )
1(
#30200
b100101110 )
0(
#30300
b10011000 >
b100101111 )
1(
#30400
b100110000 )
0(
#30500
b10011001 >
b100110001 )
1(
#30600
b100110010 )
0(
#30700
b10011010 >
b100110011 )
1(
#30800
b100110100 )
0(
#30900
b10011011 >
b100110101 )
1(
#31000
b100110110 )
0(
#31100
b10011100 >
b100110111 )
1(
#31200
b100111000 )
0(
#31300
b10011101 >
b100111001 )
1(
#31400
b100111010 )
0(
#31500
b10011110 >
b100111011 )
1(
#31600
b100111100 )
0(
#31700
b10011111 >
b100111101 )
1(
#31800
b100111110 )
0(
#31900
b10100000 >
b100111111 )
1(
#32000
b101000000 )
0(
#32100
b10100001 >
b101000001 )
1(
#32200
b101000010 )
0(
#32300
b10100010 >
b101000011 )
1(
#32400
b101000100 )
0(
#32500
b10100011 >
b101000101 )
1(
#32600
b101000110 )
0(
#32700
b10100100 >
b101000111 )
1(
#32800
b101001000 )
0(
#32900
b10100101 >
b101001001 )
1(
#33000
b101001010 )
0(
#33100
b10100110 >
b101001011 )
1(
#33200
b101001100 )
0(
#33300
b10100111 >
b101001101 )
1(
#33400
b101001110 )
0(
#33500
b10101000 >
b101001111 )
1(
#33600
b101010000 )
0(
#33700
b10101001 >
b101010001 )
1(
#33800
b101010010 )
0(
#33900
b10101010 >
b101010011 )
1(
#34000
b101010100 )
0(
#34100
b10101011 >
b101010101 )
1(
#34200
b101010110 )
0(
#34300
b10101100 >
b101010111 )
1(
#34400
b101011000 )
0(
#34500
b10101101 >
b101011001 )
1(
#34600
b101011010 )
0(
#34700
b10101110 >
b101011011 )
1(
#34800
b101011100 )
0(
#34900
b10101111 >
b101011101 )
1(
#35000
b101011110 )
0(
#35100
b10110000 >
b101011111 )
1(
#35200
b101100000 )
0(
#35300
b10110001 >
b101100001 )
1(
#35400
b101100010 )
0(
#35500
b10110010 >
b101100011 )
1(
#35600
b101100100 )
0(
#35700
b10110011 >
b101100101 )
1(
#35800
b101100110 )
0(
#35900
b10110100 >
b101100111 )
1(
#36000
b101101000 )
0(
#36100
b10110101 >
b101101001 )
1(
#36200
b101101010 )
0(
#36300
b10110110 >
b101101011 )
1(
#36400
b101101100 )
0(
#36500
b10110111 >
b101101101 )
1(
#36600
b101101110 )
0(
#36700
b10111000 >
b101101111 )
1(
#36800
b101110000 )
0(
#36900
b10111001 >
b101110001 )
1(
#37000
b101110010 )
0(
#37100
b10111010 >
b101110011 )
1(
#37200
b101110100 )
0(
#37300
b10111011 >
b101110101 )
1(
#37400
b101110110 )
0(
#37500
b10111100 >
b101110111 )
1(
#37600
b101111000 )
0(
#37700
b10111101 >
b101111001 )
1(
#37800
b101111010 )
0(
#37900
b10111110 >
b101111011 )
1(
#38000
b101111100 )
0(
#38100
b10111111 >
b101111101 )
1(
#38200
b101111110 )
0(
#38300
b11000000 >
b101111111 )
1(
#38400
b110000000 )
0(
#38500
b11000001 >
b110000001 )
1(
#38600
b110000010 )
0(
#38700
b11000010 >
b110000011 )
1(
#38800
b110000100 )
0(
#38900
b11000011 >
b110000101 )
1(
#39000
b110000110 )
0(
#39100
b11000100 >
b110000111 )
1(
#39200
b110001000 )
0(
#39300
b11000101 >
b110001001 )
1(
#39400
b110001010 )
0(
#39500
b11000110 >
b110001011 )
1(
#39600
b110001100 )
0(
#39700
b11000111 >
b110001101 )
1(
#39800
b110001110 )
0(
#39900
b11001000 >
b110001111 )
1(
#40000
b110010000 )
0(
#40100
b11001001 >
b110010001 )
1(
#40200
b110010010 )
0(
#40300
b11001010 >
b110010011 )
1(
#40400
b110010100 )
0(
#40500
b11001011 >
b110010101 )
1(
#40600
b110010110 )
0(
#40700
b11001100 >
b110010111 )
1(
#40800
b110011000 )
0(
#40900
b11001101 >
b110011001 )
1(
#41000
b110011010 )
0(
#41100
b11001110 >
b110011011 )
1(
#41200
b110011100 )
0(
#41300
b11001111 >
b110011101 )
1(
#41400
b110011110 )
0(
#41500
b11010000 >
b110011111 )
1(
#41600
b110100000 )
0(
#41700
b11010001 >
b110100001 )
1(
#41800
b110100010 )
0(
#41900
b11010010 >
b110100011 )
1(
#42000
b110100100 )
0(
#42100
b11010011 >
b110100101 )
1(
#42200
b110100110 )
0(
#42300
b11010100 >
b110100111 )
1(
#42400
b110101000 )
0(
#42500
b11010101 >
b110101001 )
1(
#42600
b110101010 )
0(
#42700
b11010110 >
b110101011 )
1(
#42800
b110101100 )
0(
#42900
b11010111 >
b110101101 )
1(
#43000
b110101110 )
0(
#43100
b11011000 >
b110101111 )
1(
#43200
b110110000 )
0(
#43300
b11011001 >
b110110001 )
1(
#43400
b110110010 )
0(
#43500
b11011010 >
b110110011 )
1(
#43600
b110110100 )
0(
#43700
b11011011 >
b110110101 )
1(
#43800
b110110110 )
0(
#43900
b11011100 >
b110110111 )
1(
#44000
b110111000 )
0(
#44100
b11011101 >
b110111001 )
1(
#44200
b110111010 )
0(
#44300
b11011110 >
b110111011 )
1(
#44400
b110111100 )
0(
#44500
b11011111 >
b110111101 )
1(
#44600
b110111110 )
0(
#44700
b11100000 >
b110111111 )
1(
#44800
b111000000 )
0(
#44900
b11100001 >
b111000001 )
1(
#45000
b111000010 )
0(
#45100
b11100010 >
b111000011 )
1(
#45200
b111000100 )
0(
#45300
b11100011 >
b111000101 )
1(
#45400
b111000110 )
0(
#45500
b11100100 >
b111000111 )
1(
#45600
b111001000 )
0(
#45700
b11100101 >
b111001001 )
1(
#45800
b111001010 )
0(
#45900
b11100110 >
b111001011 )
1(
#46000
b111001100 )
0(
#46100
b11100111 >
b111001101 )
1(
#46200
b111001110 )
0(
#46300
b11101000 >
b111001111 )
1(
#46400
b111010000 )
0(
#46500
b11101001 >
b111010001 )
1(
#46600
b111010010 )
0(
#46700
b11101010 >
b111010011 )
1(
#46800
b111010100 )
0(
#46900
b11101011 >
b111010101 )
1(
#47000
b111010110 )
0(
#47100
b11101100 >
b111010111 )
1(
#47200
b111011000 )
0(
#47300
b11101101 >
b111011001 )
1(
#47400
b111011010 )
0(
#47500
b11101110 >
b111011011 )
1(
#47600
b111011100 )
0(
#47700
b11101111 >
b111011101 )
1(
#47800
b111011110 )
0(
#47900
b11110000 >
b111011111 )
1(
#48000
b111100000 )
0(
#48100
b11110001 >
b111100001 )
1(
#48200
b111100010 )
0(
#48300
b11110010 >
b111100011 )
1(
#48400
b111100100 )
0(
#48500
b11110011 >
b111100101 )
1(
#48600
b111100110 )
0(
#48700
b11110100 >
b111100111 )
1(
#48800
b111101000 )
0(
#48900
b11110101 >
b111101001 )
1(
#49000
b111101010 )
0(
#49100
b11110110 >
b111101011 )
1(
#49200
b111101100 )
0(
#49300
b11110111 >
b111101101 )
1(
#49400
b111101110 )
0(
#49500
b11111000 >
b111101111 )
1(
#49600
b111110000 )
0(
#49700
b11111001 >
b111110001 )
1(
#49800
b111110010 )
0(
#49900
b11111010 >
b111110011 )
1(
#50000
b111110100 )
0(
#50100
b11111011 >
b111110101 )
1(
#50200
b111110110 )
0(
#50300
b11111100 >
b111110111 )
1(
#50400
b111111000 )
0(
#50500
b11111101 >
b111111001 )
1(
#50600
b111111010 )
0(
#50700
b11111110 >
b111111011 )
1(
#50800
b111111100 )
0(
#50900
b11111111 >
b111111101 )
1(
#51000
b111111110 )
0(
#51100
b100000000 >
b111111111 )
1(
#51200
b1000000000 )
0(
#51300
b100000001 >
b1000000001 )
1(
#51400
b1000000010 )
0(
#51500
b100000010 >
b1000000011 )
1(
#51600
b1000000100 )
0(
#51700
b100000011 >
b1000000101 )
1(
#51800
b1000000110 )
0(
#51900
b100000100 >
b1000000111 )
1(
#52000
b1000001000 )
0(
#52100
b100000101 >
b1000001001 )
1(
#52200
b1000001010 )
0(
#52300
b100000110 >
b1000001011 )
1(
#52400
b1000001100 )
0(
#52500
b100000111 >
b1000001101 )
1(
#52600
b1000001110 )
0(
#52700
b100001000 >
b1000001111 )
1(
#52800
b1000010000 )
0(
#52900
b100001001 >
b1000010001 )
1(
#53000
b1000010010 )
0(
#53100
b100001010 >
b1000010011 )
1(
#53200
b1000010100 )
0(
#53300
b100001011 >
b1000010101 )
1(
#53400
b1000010110 )
0(
#53500
b100001100 >
b1000010111 )
1(
#53600
b1000011000 )
0(
#53700
b100001101 >
b1000011001 )
1(
#53800
b1000011010 )
0(
#53900
b100001110 >
b1000011011 )
1(
#54000
b1000011100 )
0(
#54100
b100001111 >
b1000011101 )
1(
#54200
b1000011110 )
0(
#54300
b100010000 >
b1000011111 )
1(
#54400
b1000100000 )
0(
#54500
b100010001 >
b1000100001 )
1(
#54600
b1000100010 )
0(
#54700
b100010010 >
b1000100011 )
1(
#54800
b1000100100 )
0(
#54900
b100010011 >
b1000100101 )
1(
#55000
b1000100110 )
0(
#55100
b100010100 >
b1000100111 )
1(
#55200
b1000101000 )
0(
#55300
b100010101 >
b1000101001 )
1(
#55400
b1000101010 )
0(
#55500
b100010110 >
b1000101011 )
1(
#55600
b1000101100 )
0(
#55700
b100010111 >
b1000101101 )
1(
#55800
b1000101110 )
0(
#55900
b100011000 >
b1000101111 )
1(
#56000
b1000110000 )
0(
#56100
b100011001 >
b1000110001 )
1(
#56200
b1000110010 )
0(
#56300
b100011010 >
b1000110011 )
1(
#56400
b1000110100 )
0(
#56500
b100011011 >
b1000110101 )
1(
#56600
b1000110110 )
0(
#56700
b100011100 >
b1000110111 )
1(
#56800
b1000111000 )
0(
#56900
b100011101 >
b1000111001 )
1(
#57000
b1000111010 )
0(
#57100
b100011110 >
b1000111011 )
1(
#57200
b1000111100 )
0(
#57300
b100011111 >
b1000111101 )
1(
#57400
b1000111110 )
0(
#57500
b100100000 >
b1000111111 )
1(
#57600
b1001000000 )
0(
#57700
b100100001 >
b1001000001 )
1(
#57800
b1001000010 )
0(
#57900
b100100010 >
b1001000011 )
1(
#58000
b1001000100 )
0(
#58100
b100100011 >
b1001000101 )
1(
#58200
b1001000110 )
0(
#58300
b100100100 >
b1001000111 )
1(
#58400
b1001001000 )
0(
#58500
b100100101 >
b1001001001 )
1(
#58600
b1001001010 )
0(
#58700
b100100110 >
b1001001011 )
1(
#58800
b1001001100 )
0(
#58900
b100100111 >
b1001001101 )
1(
#59000
b1001001110 )
0(
#59100
b100101000 >
b1001001111 )
1(
#59200
b1001010000 )
0(
#59300
b100101001 >
b1001010001 )
1(
#59400
b1001010010 )
0(
#59500
b100101010 >
b1001010011 )
1(
#59600
b1001010100 )
0(
#59700
b100101011 >
b1001010101 )
1(
#59800
b1001010110 )
0(
#59900
b100101100 >
b1001010111 )
1(
#60000
b1001011000 )
0(
#60100
b100101101 >
b1001011001 )
1(
#60200
b1001011010 )
0(
#60300
b100101110 >
b1001011011 )
1(
#60400
b1001011100 )
0(
#60500
b100101111 >
b1001011101 )
1(
#60600
b1001011110 )
0(
#60700
b100110000 >
b1001011111 )
1(
#60800
b1001100000 )
0(
#60900
b100110001 >
b1001100001 )
1(
#61000
b1001100010 )
0(
#61100
b100110010 >
b1001100011 )
1(
#61200
b1001100100 )
0(
#61300
b100110011 >
b1001100101 )
1(
#61400
b1001100110 )
0(
#61500
b100110100 >
b1001100111 )
1(
#61600
b1001101000 )
0(
#61700
b100110101 >
b1001101001 )
1(
#61800
b1001101010 )
0(
#61900
b100110110 >
b1001101011 )
1(
#62000
b1001101100 )
0(
#62100
b100110111 >
b1001101101 )
1(
#62200
b1001101110 )
0(
#62300
b100111000 >
b1001101111 )
1(
#62400
b1001110000 )
0(
#62500
b100111001 >
b1001110001 )
1(
#62600
b1001110010 )
0(
#62700
b100111010 >
b1001110011 )
1(
#62800
b1001110100 )
0(
#62900
b100111011 >
b1001110101 )
1(
#63000
b1001110110 )
0(
#63100
b100111100 >
b1001110111 )
1(
#63200
b1001111000 )
0(
#63300
b100111101 >
b1001111001 )
1(
#63400
b1001111010 )
0(
#63500
b100111110 >
b1001111011 )
1(
#63600
b1001111100 )
0(
#63700
b100111111 >
b1001111101 )
1(
#63800
b1001111110 )
0(
#63900
b101000000 >
b1001111111 )
1(
#64000
b1010000000 )
0(
#64100
b101000001 >
b1010000001 )
1(
#64200
b1010000010 )
0(
#64300
b101000010 >
b1010000011 )
1(
#64400
b1010000100 )
0(
#64500
b101000011 >
b1010000101 )
1(
#64600
b1010000110 )
0(
#64700
b101000100 >
b1010000111 )
1(
#64800
b1010001000 )
0(
#64900
b101000101 >
b1010001001 )
1(
#65000
b1010001010 )
0(
#65100
b101000110 >
b1010001011 )
1(
#65200
b1010001100 )
0(
#65300
b101000111 >
b1010001101 )
1(
#65400
b1010001110 )
0(
#65500
b101001000 >
b1010001111 )
1(
#65600
b1010010000 )
0(
#65700
b101001001 >
b1010010001 )
1(
#65800
b1010010010 )
0(
#65900
b101001010 >
b1010010011 )
1(
#66000
b1010010100 )
0(
#66100
b101001011 >
b1010010101 )
1(
#66200
b1010010110 )
0(
#66300
b101001100 >
b1010010111 )
1(
#66400
b1010011000 )
0(
#66500
b101001101 >
b1010011001 )
1(
#66600
b1010011010 )
0(
#66700
b101001110 >
b1010011011 )
1(
#66800
b1010011100 )
0(
#66900
b101001111 >
b1010011101 )
1(
#67000
b1010011110 )
0(
#67100
b101010000 >
b1010011111 )
1(
#67200
b1010100000 )
0(
#67300
b101010001 >
b1010100001 )
1(
#67400
b1010100010 )
0(
#67500
b101010010 >
b1010100011 )
1(
#67600
b1010100100 )
0(
#67700
b101010011 >
b1010100101 )
1(
#67800
b1010100110 )
0(
#67900
b101010100 >
b1010100111 )
1(
#68000
b1010101000 )
0(
#68100
b101010101 >
b1010101001 )
1(
#68200
b1010101010 )
0(
#68300
b101010110 >
b1010101011 )
1(
#68400
b1010101100 )
0(
#68500
b101010111 >
b1010101101 )
1(
#68600
b1010101110 )
0(
