Homework/homework3/test.v
//-----------------------------------------------------
// Design Name : parity_using_function2
// File Name   : parity_using_function2.v
// Function    : Parity using function
// Coder       : Deepak Kumar Tala
//-----------------------------------------------------
module test (data_in, parity_out);
output reg parity_out ;
input [7:0] data_in ;     

function parity;
    input [7:0] data; 
    integer i; 
    begin 
        parity = 0; 
        for (i = 0; i < 8; i = i + 1) begin  
            parity = parity ^ data[i]; 
        end 
    end 
endfunction 

always @ (data_in)
    parity_out = parity(data_in);

endmodule

Homework/homework3/tb.v
`timescale 1 ns / 100 ps

module tb();

reg [7:0]in;
wire out;

test DUT (.data_in(in), .parity_out(out));


initial
  begin
    $dumpfile("test.vcd");
	$dumpvars;
  $display($time, "Starting simulation");
  in = 8'b00000000;
  while(in < 8'b1111_1111) begin
    #10 in = in + 8'b00000101;
  end
   #10 $finish;
  end

initial
  begin
    $monitor($time, "in = %b, out = %b",
	         in, out);
  end

endmodule

Homework/homework3/test.vcd
$date
	Wed Feb 12 09:12:23 2020
$end
$version
	Icarus Verilog
$end
$timescale
	100ps
$end
$scope module tb $end
$var wire 1 ! out $end
$var reg 8 " in [7:0] $end
$scope module DUT $end
$var wire 8 # data_in [7:0] $end
$var reg 1 ! parity_out $end
$scope function parity $end
$var reg 8 $ data [7:0] $end
$var reg 1 % parity $end
$var integer 32 & i [31:0] $end
$upscope $end
$upscope $end
$upscope $end
$enddefinitions $end
#0
$dumpvars
b1000 &
0%
b0 $
b0 #
b0 "
0!
$end
#100
0%
b1000 &
b101 $
b101 "
b101 #
#200
0%
b1000 &
b1010 $
b1010 "
b1010 #
#300
0%
b1000 &
b1111 $
b1111 "
b1111 #
#400
0%
b1000 &
b10100 $
b10100 "
b10100 #
#500
1!
1%
b1000 &
b11001 $
b11001 "
b11001 #
#600
0!
b1000 &
0%
b11110 $
b11110 "
b11110 #
#700
1!
1%
b1000 &
b100011 $
b100011 "
b100011 #
#800
0!
b1000 &
0%
b101000 $
b101000 "
b101000 #
#900
0%
b1000 &
b101101 $
b101101 "
b101101 #
#1000
1!
1%
b1000 &
b110010 $
b110010 "
b110010 #
#1100
b1000 &
1%
b110111 $
b110111 "
b110111 #
#1200
0!
b1000 &
0%
b111100 $
b111100 "
b111100 #
#1300
0%
b1000 &
b1000001 $
b1000001 "
b1000001 #
#1400
1!
1%
b1000 &
b1000110 $
b1000110 "
b1000110 #
#1500
0!
b1000 &
0%
b1001011 $
b1001011 "
b1001011 #
#1600
0%
b1000 &
b1010000 $
b1010000 "
b1010000 #
#1700
0%
b1000 &
b1010101 $
b1010101 "
b1010101 #
#1800
0%
b1000 &
b1011010 $
b1011010 "
b1011010 #
#1900
0%
b1000 &
b1011111 $
b1011111 "
b1011111 #
#2000
1!
1%
b1000 &
b1100100 $
b1100100 "
b1100100 #
#2100
0!
b1000 &
0%
b1101001 $
b1101001 "
b1101001 #
#2200
1!
1%
b1000 &
b1101110 $
b1101110 "
b1101110 #
#2300
b1000 &
1%
b1110011 $
b1110011 "
b1110011 #
#2400
0!
b1000 &
0%
b1111000 $
b1111000 "
b1111000 #
#2500
0%
b1000 &
b1111101 $
b1111101 "
b1111101 #
#2600
0%
b1000 &
b10000010 $
b10000010 "
b10000010 #
#2700
0%
b1000 &
b10000111 $
b10000111 "
b10000111 #
#2800
1!
1%
b1000 &
b10001100 $
b10001100 "
b10001100 #
#2900
b1000 &
1%
b10010001 $
b10010001 "
b10010001 #
#3000
0!
b1000 &
0%
b10010110 $
b10010110 "
b10010110 #
#3100
1!
1%
b1000 &
b10011011 $
b10011011 "
b10011011 #
#3200
0!
b1000 &
0%
b10100000 $
b10100000 "
b10100000 #
#3300
0%
b1000 &
b10100101 $
b10100101 "
b10100101 #
#3400
0%
b1000 &
b10101010 $
b10101010 "
b10101010 #
#3500
0%
b1000 &
b10101111 $
b10101111 "
b10101111 #
#3600
0%
b1000 &
b10110100 $
b10110100 "
b10110100 #
#3700
1!
1%
b1000 &
b10111001 $
b10111001 "
b10111001 #
#3800
0!
b1000 &
0%
b10111110 $
b10111110 "
b10111110 #
#3900
0%
b1000 &
b11000011 $
b11000011 "
b11000011 #
#4000
1!
1%
b1000 &
b11001000 $
b11001000 "
b11001000 #
#4100
b1000 &
1%
b11001101 $
b11001101 "
b11001101 #
#4200
0!
b1000 &
0%
b11010010 $
b11010010 "
b11010010 #
#4300
0%
b1000 &
b11010111 $
b11010111 "
b11010111 #
#4400
1!
1%
b1000 &
b11011100 $
b11011100 "
b11011100 #
#4500
0!
b1000 &
0%
b11100001 $
b11100001 "
b11100001 #
#4600
1!
1%
b1000 &
b11100110 $
b11100110 "
b11100110 #
#4700
0!
b1000 &
0%
b11101011 $
b11101011 "
b11101011 #
#4800
0%
b1000 &
b11110000 $
b11110000 "
b11110000 #
#4900
0%
b1000 &
b11110101 $
b11110101 "
b11110101 #
#5000
0%
b1000 &
b11111010 $
b11111010 "
b11111010 #
#5100
0%
b1000 &
b11111111 $
b11111111 "
b11111111 #
