Project 1/sevenSeg.v
module sevenSeg (input [3:0] val, output reg [7:0] seg);

always @(val)
  begin
    case(val)
      4'b0000 : seg = 8'b11000000;
      4'b0001 : seg = 8'b11111001;
      4'b0010 : seg = 8'b10100100;
      4'b0011 : seg = 8'b10110000;
      4'b0100 : seg = 8'b10011001;
      4'b0101 : seg = 8'b10010010;
      4'b0110 : seg = 8'b10000010;
      4'b0111 : seg = 8'b11111000;
      4'b1000 : seg = 8'b10000000;
      4'b1001 : seg = 8'b10011000;
      4'b1010 : seg = 8'b00001000;
      4'b1011 : seg = 8'b00000000;
      4'b1100 : seg = 8'b01000110;
      4'b1101 : seg = 8'b01000000;
      4'b1110 : seg = 8'b00000110;
      4'b1111 : seg = 8'b00001110;
      default : seg = 8'b00000000;
    endcase
  end
endmodule

Project 1/design2.v
module design2 (switches, leds, hex0, hex1, hex2, hex3, hex4, hex5);

input [9:0] switches;
output reg [9:0] leds;
output [7:0] hex0;
output reg [7:0] hex1;
output reg [7:0] hex2;
output reg [7:0] hex3;
output [7:0] hex4;
output reg [7:0] hex5;

sevenSeg U0 (.val(switches[3:0]), .seg(hex0));
sevenSeg U1 (.val(switches[7:4]), .seg(hex4));

always@ (switches[7:0])
begin
    leds[8] = 1'b0;
    leds[9] = 1'b0;
    hex2 = 8'b1111_1111;
    hex3 = 8'b1111_1111;
    if (switches[7:4] > switches[3:0])
    begin
        leds[0] = 1'b0;
        leds[1] = 1'b1;
        leds[2] = 1'b0;
        hex1 = 8'b1100_0111;
        hex5 = 8'b1111_1111;
    end
    else if (switches[7:4] < switches[3:0])
    begin
        leds[0] = 1'b1;
        leds[1] = 1'b0;
        leds[2] = 1'b0;
        hex1 = 8'b1111_1111;
        hex5 = 8'b1100_0111;
    end
    else
    begin
        leds[0] = 1'b0;
        leds[1] = 1'b0;
        leds[2] = 1'b1;
        hex1 = 8'b1000_0110;
        hex5 = 8'b1000_0110;
    end
end
endmodule

Project 1/design1.v
//The purpose of this design is to have LEDR[7:0] to be controlled by SW[7:0], and have KEY[0] invert the values. Additionally, HEX[5:0] are used to display lab partners birthday, and when KEY[1] is high, change to my birthday
module design1 (switch,key,leds,hex0,hex1,hex2,hex3,hex4,hex5);

input [9:0] switch;
input [1:0] key;
output reg [9:0] leds;
output [7:0] hex0;
output [7:0] hex1;
output [7:0] hex2;
output [7:0] hex3;
output [7:0] hex4;
output [7:0] hex5;

//Light the leds based on the switch positions, and invert the leds when key0 is high
always @(key[0])
begin
  leds[7:0] = 8'b00000000;
  if(key[0])
  begin
    leds[7:0] = switch;
  end
  else
  begin
    leds[7:0] = ~switch;
  end
end

//seg2 is a reg for the display that needs to be changed
reg [3:0] seg2 = 4'b0011;
sevenSeg S2(.val(seg2), .seg(hex2));

//These displays stay the same between the two dates
sevenSeg S0(.val(4'b0001), .seg(hex0));
sevenSeg S1(.val(4'b0000), .seg(hex1));
sevenSeg S3(.val(4'b0010), .seg(hex3));
sevenSeg S4(.val(4'b1000), .seg(hex4));
sevenSeg S5(.val(4'b0000), .seg(hex5));


//Changing the displays that need to be changed based on key1
always @(key[1])
begin
  if(key[1])
  begin
    seg2 = 4'b0011;
  end
  else
  begin
    seg2 = 4'b0100;
  end
end

endmodule

Project 1/top.v
module top (SW, KEY, LEDR, HEX0, HEX1, HEX2, HEX3, HEX4, HEX5);

input [9:0] SW;
input [1:0] KEY;
output reg [9:0] LEDR;
output reg [7:0] HEX0;
output reg [7:0] HEX1;
output reg [7:0] HEX2;
output reg [7:0] HEX3;
output reg [7:0] HEX4;
output reg [7:0] HEX5;

wire [9:0] ledsa;
wire [7:0] hex0a;
wire [7:0] hex1a;
wire [7:0] hex2a;
wire [7:0] hex3a;
wire [7:0] hex4a;
wire [7:0] hex5a;

wire [9:0] ledsb;
wire [7:0] hex0b;
wire [7:0] hex1b;
wire [7:0] hex2b;
wire [7:0] hex3b;
wire [7:0] hex4b;
wire [7:0] hex5b;

design1 U0(.switch(SW), .key(KEY), .leds(ledsa),.hex0(hex0a),.hex1(hex1a),.hex2(hex2a),.hex3(hex3a),.hex4(hex4a),.hex5(hex5a));
design2 U1(.switches(SW), .leds(ledsb),.hex0(hex0b),.hex1(hex1b),.hex2(hex2b),.hex3(hex3b),.hex4(hex4b),.hex5(hex5b));

always @(SW[9]) begin
  if(SW[9])
  begin
    LEDR = ledsa;
    HEX0 = hex0a;
    HEX1 = hex1a;
    HEX2 = hex2a;
    HEX3 = hex3a;
    HEX4 = hex4a;
    HEX5 = hex5a;
  end
  else
  begin
    LEDR = ledsb;
    HEX0 = hex0b;
    HEX1 = hex1b;
    HEX2 = hex2b;
    HEX3 = hex3b;
    HEX4 = hex4b;
    HEX5 = hex5b;
  end
end

endmodule

Project 1/tb1.v
`timescale 1 ns / 100 ps

module tb1();

reg [9:0] testSW;
reg [1:0] testKEY;
wire [9:0] testLED;
wire [7:0] testHEX0;
wire [7:0] testHEX1;
wire [7:0] testHEX2;
wire [7:0] testHEX3;
wire [7:0] testHEX4;
wire [7:0] testHEX5;

design1 DUT(.switch(testSW), .key(testKEY), .leds(testLED),.hex0(testHEX0),.hex1(testHEX1),.hex2(testHEX2),.hex3(testHEX3),.hex4(testHEX4),.hex5(testHEX5));

// Begin stimulating inputs:
initial begin
  $dumpfile("test.vcd");
  $dumpvars;
  $display($time, "Starting simulation");

  //Initialize inputs:
  testSW = 10'b0000000000;
  testKEY = 2'b00;

  // Test birthday switch:
  #10 testKEY = 2'b10;

  // Test LED switching:
  while(testSW < 10'b1111_1111) begin
    #10 testSW = testSW + 10'b00000001;
  end

  // End testing
  #10 $finish;
end

// Monitor inputs and outputs
initial
  begin
    $monitor($time, "testSW = %b, testKEY = %b, testLED = %b, testHEX0 = %b, testHEX1 = %b, testHEX2 = %b, testHEX3 = %b, testHEX4 = %b, testHEX5 = %b",
           testSW, testKEY, testLED, testHEX0, testHEX1, testHEX2, testHEX3, testHEX4, testHEX5);
  end
endmodule

Project 1/test.vcd
$date
	Sun Feb 16 10:53:28 2020
$end
$version
	Icarus Verilog
$end
$timescale
	100ps
$end
$scope module tb1 $end
$var wire 10 ! testLED [9:0] $end
$var wire 8 " testHEX5 [7:0] $end
$var wire 8 # testHEX4 [7:0] $end
$var wire 8 $ testHEX3 [7:0] $end
$var wire 8 % testHEX2 [7:0] $end
$var wire 8 & testHEX1 [7:0] $end
$var wire 8 ' testHEX0 [7:0] $end
$var reg 2 ( testKEY [1:0] $end
$var reg 10 ) testSW [9:0] $end
$scope module DUT $end
$var wire 2 * key [1:0] $end
$var wire 10 + switch [9:0] $end
$var wire 8 , hex5 [7:0] $end
$var wire 8 - hex4 [7:0] $end
$var wire 8 . hex3 [7:0] $end
$var wire 8 / hex2 [7:0] $end
$var wire 8 0 hex1 [7:0] $end
$var wire 8 1 hex0 [7:0] $end
$var reg 10 2 leds [9:0] $end
$var reg 4 3 seg2 [3:0] $end
$scope module S0 $end
$var wire 4 4 val [3:0] $end
$var reg 8 5 seg [7:0] $end
$upscope $end
$scope module S1 $end
$var wire 4 6 val [3:0] $end
$var reg 8 7 seg [7:0] $end
$upscope $end
$scope module S2 $end
$var wire 4 8 val [3:0] $end
$var reg 8 9 seg [7:0] $end
$upscope $end
$scope module S3 $end
$var wire 4 : val [3:0] $end
$var reg 8 ; seg [7:0] $end
$upscope $end
$scope module S4 $end
$var wire 4 < val [3:0] $end
$var reg 8 = seg [7:0] $end
$upscope $end
$scope module S5 $end
$var wire 4 > val [3:0] $end
$var reg 8 ? seg [7:0] $end
$upscope $end
$upscope $end
$upscope $end
$scope module top $end
$var wire 2 @ KEY [1:0] $end
$var wire 10 A SW [9:0] $end
$var wire 10 B ledsb [9:0] $end
$var wire 10 C ledsa [9:0] $end
$var wire 8 D hex5b [7:0] $end
$var wire 8 E hex5a [7:0] $end
$var wire 8 F hex4b [7:0] $end
$var wire 8 G hex4a [7:0] $end
$var wire 8 H hex3b [7:0] $end
$var wire 8 I hex3a [7:0] $end
$var wire 8 J hex2b [7:0] $end
$var wire 8 K hex2a [7:0] $end
$var wire 8 L hex1b [7:0] $end
$var wire 8 M hex1a [7:0] $end
$var wire 8 N hex0b [7:0] $end
$var wire 8 O hex0a [7:0] $end
$var reg 8 P HEX0 [7:0] $end
$var reg 8 Q HEX1 [7:0] $end
$var reg 8 R HEX2 [7:0] $end
$var reg 8 S HEX3 [7:0] $end
$var reg 8 T HEX4 [7:0] $end
$var reg 8 U HEX5 [7:0] $end
$var reg 10 V LEDR [9:0] $end
$scope module U0 $end
$var wire 2 W key [1:0] $end
$var wire 10 X switch [9:0] $end
$var wire 8 Y hex5 [7:0] $end
$var wire 8 Z hex4 [7:0] $end
$var wire 8 [ hex3 [7:0] $end
$var wire 8 \ hex2 [7:0] $end
$var wire 8 ] hex1 [7:0] $end
$var wire 8 ^ hex0 [7:0] $end
$var reg 10 _ leds [9:0] $end
$var reg 4 ` seg2 [3:0] $end
$scope module S0 $end
$var wire 4 a val [3:0] $end
$var reg 8 b seg [7:0] $end
$upscope $end
$scope module S1 $end
$var wire 4 c val [3:0] $end
$var reg 8 d seg [7:0] $end
$upscope $end
$scope module S2 $end
$var wire 4 e val [3:0] $end
$var reg 8 f seg [7:0] $end
$upscope $end
$scope module S3 $end
$var wire 4 g val [3:0] $end
$var reg 8 h seg [7:0] $end
$upscope $end
$scope module S4 $end
$var wire 4 i val [3:0] $end
$var reg 8 j seg [7:0] $end
$upscope $end
$scope module S5 $end
$var wire 4 k val [3:0] $end
$var reg 8 l seg [7:0] $end
$upscope $end
$upscope $end
$scope module U1 $end
$var wire 10 m switches [9:0] $end
$var wire 8 n hex4 [7:0] $end
$var wire 8 o hex0 [7:0] $end
$var reg 8 p hex1 [7:0] $end
$var reg 8 q hex2 [7:0] $end
$var reg 8 r hex3 [7:0] $end
$var reg 8 s hex5 [7:0] $end
$var reg 10 t leds [9:0] $end
$scope module U0 $end
$var wire 4 u val [3:0] $end
$var reg 8 v seg [7:0] $end
$upscope $end
$scope module U1 $end
$var wire 4 w val [3:0] $end
$var reg 8 x seg [7:0] $end
$upscope $end
$upscope $end
$upscope $end
$enddefinitions $end
#0
$dumpvars
b0 x
bz w
b0 v
bz u
b0xxxxx100 t
b10000110 s
b11111111 r
b11111111 q
b10000110 p
b0 o
b0 n
bz m
b11000000 l
b0 k
b10000000 j
b1000 i
b10100100 h
b10 g
b10011001 f
b100 e
b11000000 d
b0 c
b11111001 b
b1 a
b100 `
bx _
b11111001 ^
b11000000 ]
b10011001 \
b10100100 [
b10000000 Z
b11000000 Y
bz X
bz W
b0xxxxx100 V
b10000110 U
b0 T
b11111111 S
b11111111 R
b10000110 Q
b0 P
b11111001 O
b0 N
b11000000 M
b10000110 L
b10011001 K
b11111111 J
b10100100 I
b11111111 H
b10000000 G
b0 F
b11000000 E
b10000110 D
bx C
b0xxxxx100 B
bz A
bz @
b11000000 ?
b0 >
b10000000 =
b1000 <
b10100100 ;
b10 :
b10011001 9
b100 8
b11000000 7
b0 6
b11111001 5
b1 4
b100 3
bx11111111 2
b11111001 1
b11000000 0
b10011001 /
b10100100 .
b10000000 -
b11000000 ,
b0 +
b0 *
b0 )
b0 (
b11111001 '
b11000000 &
b10011001 %
b10100100 $
b10000000 #
b11000000 "
bx11111111 !
$end
#100
b10110000 %
b10110000 /
b10110000 9
b11 3
b11 8
b10 (
b10 *
#200
b1 )
b1 +
#300
b10 )
b10 +
#400
b11 )
b11 +
#500
b100 )
b100 +
#600
b101 )
b101 +
#700
b110 )
b110 +
#800
b111 )
b111 +
#900
b1000 )
b1000 +
#1000
b1001 )
b1001 +
#1100
b1010 )
b1010 +
#1200
b1011 )
b1011 +
#1300
b1100 )
b1100 +
#1400
b1101 )
b1101 +
#1500
b1110 )
b1110 +
#1600
b1111 )
b1111 +
#1700
b10000 )
b10000 +
#1800
b10001 )
b10001 +
#1900
b10010 )
b10010 +
#2000
b10011 )
b10011 +
#2100
b10100 )
b10100 +
#2200
b10101 )
b10101 +
#2300
b10110 )
b10110 +
#2400
b10111 )
b10111 +
#2500
b11000 )
b11000 +
#2600
b11001 )
b11001 +
#2700
b11010 )
b11010 +
#2800
b11011 )
b11011 +
#2900
b11100 )
b11100 +
#3000
b11101 )
b11101 +
#3100
b11110 )
b11110 +
#3200
b11111 )
b11111 +
#3300
b100000 )
b100000 +
#3400
b100001 )
b100001 +
#3500
b100010 )
b100010 +
#3600
b100011 )
b100011 +
#3700
b100100 )
b100100 +
#3800
b100101 )
b100101 +
#3900
b100110 )
b100110 +
#4000
b100111 )
b100111 +
#4100
b101000 )
b101000 +
#4200
b101001 )
b101001 +
#4300
b101010 )
b101010 +
#4400
b101011 )
b101011 +
#4500
b101100 )
b101100 +
#4600
b101101 )
b101101 +
#4700
b101110 )
b101110 +
#4800
b101111 )
b101111 +
#4900
b110000 )
b110000 +
#5000
b110001 )
b110001 +
#5100
b110010 )
b110010 +
#5200
b110011 )
b110011 +
#5300
b110100 )
b110100 +
#5400
b110101 )
b110101 +
#5500
b110110 )
b110110 +
#5600
b110111 )
b110111 +
#5700
b111000 )
b111000 +
#5800
b111001 )
b111001 +
#5900
b111010 )
b111010 +
#6000
b111011 )
b111011 +
#6100
b111100 )
b111100 +
#6200
b111101 )
b111101 +
#6300
b111110 )
b111110 +
#6400
b111111 )
b111111 +
#6500
b1000000 )
b1000000 +
#6600
b1000001 )
b1000001 +
#6700
b1000010 )
b1000010 +
#6800
b1000011 )
b1000011 +
#6900
b1000100 )
b1000100 +
#7000
b1000101 )
b1000101 +
#7100
b1000110 )
b1000110 +
#7200
b1000111 )
b1000111 +
#7300
b1001000 )
b1001000 +
#7400
b1001001 )
b1001001 +
#7500
b1001010 )
b1001010 +
#7600
b1001011 )
b1001011 +
#7700
b1001100 )
b1001100 +
#7800
b1001101 )
b1001101 +
#7900
b1001110 )
b1001110 +
#8000
b1001111 )
b1001111 +
#8100
b1010000 )
b1010000 +
#8200
b1010001 )
b1010001 +
#8300
b1010010 )
b1010010 +
#8400
b1010011 )
b1010011 +
#8500
b1010100 )
b1010100 +
#8600
b1010101 )
b1010101 +
#8700
b1010110 )
b1010110 +
#8800
b1010111 )
b1010111 +
#8900
b1011000 )
b1011000 +
#9000
b1011001 )
b1011001 +
#9100
b1011010 )
b1011010 +
#9200
b1011011 )
b1011011 +
#9300
b1011100 )
b1011100 +
#9400
b1011101 )
b1011101 +
#9500
b1011110 )
b1011110 +
#9600
b1011111 )
b1011111 +
#9700
b1100000 )
b1100000 +
#9800
b1100001 )
b1100001 +
#9900
b1100010 )
b1100010 +
#10000
b1100011 )
b1100011 +
#10100
b1100100 )
b1100100 +
#10200
b1100101 )
b1100101 +
#10300
b1100110 )
b1100110 +
#10400
b1100111 )
b1100111 +
#10500
b1101000 )
b1101000 +
#10600
b1101001 )
b1101001 +
#10700
b1101010 )
b1101010 +
#10800
b1101011 )
b1101011 +
#10900
b1101100 )
b1101100 +
#11000
b1101101 )
b1101101 +
#11100
b1101110 )
b1101110 +
#11200
b1101111 )
b1101111 +
#11300
b1110000 )
b1110000 +
#11400
b1110001 )
b1110001 +
#11500
b1110010 )
b1110010 +
#11600
b1110011 )
b1110011 +
#11700
b1110100 )
b1110100 +
#11800
b1110101 )
b1110101 +
#11900
b1110110 )
b1110110 +
#12000
b1110111 )
b1110111 +
#12100
b1111000 )
b1111000 +
#12200
b1111001 )
b1111001 +
#12300
b1111010 )
b1111010 +
#12400
b1111011 )
b1111011 +
#12500
b1111100 )
b1111100 +
#12600
b1111101 )
b1111101 +
#12700
b1111110 )
b1111110 +
#12800
b1111111 )
b1111111 +
#12900
b10000000 )
b10000000 +
#13000
b10000001 )
b10000001 +
#13100
b10000010 )
b10000010 +
#13200
b10000011 )
b10000011 +
#13300
b10000100 )
b10000100 +
#13400
b10000101 )
b10000101 +
#13500
b10000110 )
b10000110 +
#13600
b10000111 )
b10000111 +
#13700
b10001000 )
b10001000 +
#13800
b10001001 )
b10001001 +
#13900
b10001010 )
b10001010 +
#14000
b10001011 )
b10001011 +
#14100
b10001100 )
b10001100 +
#14200
b10001101 )
b10001101 +
#14300
b10001110 )
b10001110 +
#14400
b10001111 )
b10001111 +
#14500
b10010000 )
b10010000 +
#14600
b10010001 )
b10010001 +
#14700
b10010010 )
b10010010 +
#14800
b10010011 )
b10010011 +
#14900
b10010100 )
b10010100 +
#15000
b10010101 )
b10010101 +
#15100
b10010110 )
b10010110 +
#15200
b10010111 )
b10010111 +
#15300
b10011000 )
b10011000 +
#15400
b10011001 )
b10011001 +
#15500
b10011010 )
b10011010 +
#15600
b10011011 )
b10011011 +
#15700
b10011100 )
b10011100 +
#15800
b10011101 )
b10011101 +
#15900
b10011110 )
b10011110 +
#16000
b10011111 )
b10011111 +
#16100
b10100000 )
b10100000 +
#16200
b10100001 )
b10100001 +
#16300
b10100010 )
b10100010 +
#16400
b10100011 )
b10100011 +
#16500
b10100100 )
b10100100 +
#16600
b10100101 )
b10100101 +
#16700
b10100110 )
b10100110 +
#16800
b10100111 )
b10100111 +
#16900
b10101000 )
b10101000 +
#17000
b10101001 )
b10101001 +
#17100
b10101010 )
b10101010 +
#17200
b10101011 )
b10101011 +
#17300
b10101100 )
b10101100 +
#17400
b10101101 )
b10101101 +
#17500
b10101110 )
b10101110 +
#17600
b10101111 )
b10101111 +
#17700
b10110000 )
b10110000 +
#17800
b10110001 )
b10110001 +
#17900
b10110010 )
b10110010 +
#18000
b10110011 )
b10110011 +
#18100
b10110100 )
b10110100 +
#18200
b10110101 )
b10110101 +
#18300
b10110110 )
b10110110 +
#18400
b10110111 )
b10110111 +
#18500
b10111000 )
b10111000 +
#18600
b10111001 )
b10111001 +
#18700
b10111010 )
b10111010 +
#18800
b10111011 )
b10111011 +
#18900
b10111100 )
b10111100 +
#19000
b10111101 )
b10111101 +
#19100
b10111110 )
b10111110 +
#19200
b10111111 )
b10111111 +
#19300
b11000000 )
b11000000 +
#19400
b11000001 )
b11000001 +
#19500
b11000010 )
b11000010 +
#19600
b11000011 )
b11000011 +
#19700
b11000100 )
b11000100 +
#19800
b11000101 )
b11000101 +
#19900
b11000110 )
b11000110 +
#20000
b11000111 )
b11000111 +
#20100
b11001000 )
b11001000 +
#20200
b11001001 )
b11001001 +
#20300
b11001010 )
b11001010 +
#20400
b11001011 )
b11001011 +
#20500
b11001100 )
b11001100 +
#20600
b11001101 )
b11001101 +
#20700
b11001110 )
b11001110 +
#20800
b11001111 )
b11001111 +
#20900
b11010000 )
b11010000 +
#21000
b11010001 )
b11010001 +
#21100
b11010010 )
b11010010 +
#21200
b11010011 )
b11010011 +
#21300
b11010100 )
b11010100 +
#21400
b11010101 )
b11010101 +
#21500
b11010110 )
b11010110 +
#21600
b11010111 )
b11010111 +
#21700
b11011000 )
b11011000 +
#21800
b11011001 )
b11011001 +
#21900
b11011010 )
b11011010 +
#22000
b11011011 )
b11011011 +
#22100
b11011100 )
b11011100 +
#22200
b11011101 )
b11011101 +
#22300
b11011110 )
b11011110 +
#22400
b11011111 )
b11011111 +
#22500
b11100000 )
b11100000 +
#22600
b11100001 )
b11100001 +
#22700
b11100010 )
b11100010 +
#22800
b11100011 )
b11100011 +
#22900
b11100100 )
b11100100 +
#23000
b11100101 )
b11100101 +
#23100
b11100110 )
b11100110 +
#23200
b11100111 )
b11100111 +
#23300
b11101000 )
b11101000 +
#23400
b11101001 )
b11101001 +
#23500
b11101010 )
b11101010 +
#23600
b11101011 )
b11101011 +
#23700
b11101100 )
b11101100 +
#23800
b11101101 )
b11101101 +
#23900
b11101110 )
b11101110 +
#24000
b11101111 )
b11101111 +
#24100
b11110000 )
b11110000 +
#24200
b11110001 )
b11110001 +
#24300
b11110010 )
b11110010 +
#24400
b11110011 )
b11110011 +
#24500
b11110100 )
b11110100 +
#24600
b11110101 )
b11110101 +
#24700
b11110110 )
b11110110 +
#24800
b11110111 )
b11110111 +
#24900
b11111000 )
b11111000 +
#25000
b11111001 )
b11111001 +
#25100
b11111010 )
b11111010 +
#25200
b11111011 )
b11111011 +
#25300
b11111100 )
b11111100 +
#25400
b11111101 )
b11111101 +
#25500
b11111110 )
b11111110 +
#25600
b11111111 )
b11111111 +
