Project 3/sevenSeg.v
module sevenSeg (input [1:0] val, output reg [7:0] seg);

always @(val)
  begin
    case(val)
      2'b00 : seg = 8'b11000000;
      2'b01 : seg = 8'b11111001;
      2'b10 : seg = 8'b10100100;
      2'b11 : seg = 8'b10110000;
     
      default : seg = 8'b00000000;
    endcase
  end
endmodule

Project 3/blink.v
module blink (clock, hazards, reset_n, turnChange, rightLEDs, leftLEDs, hex);

input turnChange, clock, hazards, reset_n;
output reg [0:2] rightLEDs;
output reg [2:0] leftLEDs;
output [7:0] hex;


reg [1:0] blinkState;
reg [1:0] blink;
reg [1:0] next;


sevenSeg H0 (.val(blinkState), .seg(hex));

always @(blinkState or turnChange)
begin
if (blink == blinkState)
begin
    if (~hazards)
    begin
        next <= 0;
    end
end
next <= blinkState + 1;
case (blinkState)
    0 : begin
        leftLEDs <= 0;
        rightLEDs <= 0;
        end
    1 : begin
        leftLEDs <= 1;
        rightLEDs <= 1;
        end
    2 : begin
        leftLEDs <= 3;
        rightLEDs <= 3;
        end
    3 : begin
        leftLEDs <= 7;
        rightLEDs <= 7;
        end
    default: begin
        leftLEDs <= 0;
        rightLEDs <= 0;
        end
endcase
blink <= blinkState;
end

always @(posedge clock or negedge reset_n)
begin
    if (~reset_n)
    begin
        blinkState <= 0;
    end
    else
    begin
        blinkState <= next;
    end
end


endmodule

Project 3/clockDivider.v
module clockDivider(clock_in, reset_n, divide_by, clock_out);
input clock_in;
input reset_n;
input [31:0] divide_by;
output reg clock_out;

reg [22:0] clock_divider = 0;

initial begin
  clock_out = 0;
  clock_divider = 0;
end
always @(posedge clock_in or negedge reset_n)
  begin
    if (~reset_n)
      begin
        clock_out = 0;
        clock_divider = 0;
      end
    else
      begin
        if(clock_divider != divide_by - 1)
          clock_divider <= clock_divider + 1;
        else
          begin
            clock_divider <= 0;
            clock_out <= ~clock_out;
          end
      end
  end
endmodule

Project 3/top.v
module top (ADC_CLK_10, SW, KEY, LEDR, HEX0);


input ADC_CLK_10;
input [9:0] SW;
input [1:0] KEY;
wire clock;
reg reset = 1;
output reg [9:0] LEDR;
output [7:0] HEX0;
reg [2:0] left_LEDs;
reg [2:0] right_LEDs;

wire [2:0] l_LEDS;
wire [2:0] r_LEDS;

always @(l_LEDS or r_LEDS)
begin
    left_LEDs <= l_LEDS;
    right_LEDs <= r_LEDS;
end

always @ (ADC_CLK_10)
begin
  if(SW[0] || SW[1] || SW[2])
  begin
    reset = KEY[0];
  end
  else if(~SW[0] && ~SW[1] && ~SW[2])
  begin
    reset = 0;
  end
end
// Initialize for the on-board programming:
// clockDivider C0 (.clock_in(ADC_CLK_10), .reset_n(reset), .divide_by(1000000), .clock_out(clock));

// Initialize for the testbenching:
clockDivider C0 (.clock_in(ADC_CLK_10), .reset_n(KEY[0]), .divide_by(1), .clock_out(clock));

blink B0 (.clock(clock), .hazards(SW[0]), .reset_n(reset), .turnChange(KEY[1]), .rightLEDs(r_LEDS), .leftLEDs(l_LEDS), .hex(HEX0));

initial
begin
    LEDR[9:0] = 10'b0000000000;
end


always @(SW[7:0] or KEY[1] or KEY[0] or reset or clock)
begin
    //RESET
    if (~reset)
    begin
        LEDR[9:0] = 10'b0000000000;
    end
    //BEHAVIOR 1: IDLE
    else if (~SW[1] & ~SW[0] & ~SW[2] & KEY[0])
    begin
        LEDR[2:0] <= 3'b000;
        LEDR[9:7] <= 3'b000;
    end
    //BEHAVIOR 2: LEFT TURN
    else if (SW[1] & KEY[1] & ~SW[0] & ~SW[2] & KEY[0])
    begin
        LEDR[9:7] <= left_LEDs;
        LEDR[2:0] <= 3'b000;
    end
    //BEHAVIOR 3: RIGHT TURN
    else if (SW[1] & ~KEY[1] & ~SW[0] & ~SW[2] & KEY[0])
    begin
        LEDR[9:7] <= 3'b000;
        LEDR[2] <= right_LEDs[0];
        LEDR[1] <= right_LEDs[1];
        LEDR[0] <= right_LEDs[2];
    end
    //BEHAVIOR 4: LEFT BRAKE
    else if (SW[1] & KEY[1] & ~SW[0] & SW[2] & KEY[0])
    begin
        LEDR[9:7] <= left_LEDs;
        LEDR[2:0] <= 3'b111;
    end
    //BEHAVIOR 5: RIGHT BRAKE
    else if (SW[1] & ~KEY[1] & ~SW[0] & SW[2] & KEY[0])
    begin
        LEDR[9:7] <= 3'b111;
        LEDR[2] <= right_LEDs[0];
        LEDR[1] <= right_LEDs[1];
        LEDR[0] <= right_LEDs[2];
    end
    //BEHAVIOR 6: STRAIGHT BRAKE
    else if ((~SW[1] & SW[2] & KEY[0]) | (SW[0] & SW[1] & SW[2]))
    begin
        LEDR[2:0] <= 3'b111;
        LEDR[9:7] <= 3'b111;
    end
    //BEHAVIOR 7: HAZARDS
    else if (SW[0] & ~SW[2] & KEY[0])
    begin
        LEDR[9:7] <= left_LEDs;
        LEDR[2] <= right_LEDs[0];
        LEDR[1] <= right_LEDs[1];
        LEDR[0] <= right_LEDs[2];
    end
    else
    begin
        LEDR[9:0] = 10'b1111111111;
    end
end

endmodule

Project 3/tb.v
`timescale 1 ns / 100 ps

module tb();

reg [9:0] testSW;
reg [1:0] testKEY;
reg clock;
reg [7:0] counter;
wire [9:0] testLED;
wire [7:0] testHEX0;

parameter testCase = 0;


top DUT(.KEY(testKEY), .SW(testSW), .ADC_CLK_10(clock), .LEDR(testLED),.HEX0(testHEX0));

// Begin stimulating inputs:
initial begin
  $dumpfile("test.vcd");
  $dumpvars;
  $display($time, "Starting simulation");

  //Initialize inputs (started with asserted reset signal):
  testSW = 10'b0000000000;
  testKEY = 0;
  clock = 1'b0;
  counter = 0;
  // Create a clock signal that has 256 cycles
  while(counter < 8'b00100000) begin
    #10 clock = ~clock;
    // De-assert the reset signal
    if(counter > 8'b00000010)
      begin
        testKEY[0] = 1;
      end

// Based on testCase, test different aspects of the design one at a time (easier for GTKWave comprehension)
      case (testCase)

// Test Hazards:
      0: begin
        if (counter > 8'b00000100)
        begin
          testSW[0] = 1;
        end
      end

// Test Right Turn:
      1: begin
        if (counter > 8'b00000100)
        begin
          testSW[1] = 1;
          testKEY[1] = 0;
        end
      end

// Test Left Turn:
      2: begin
        if (counter > 8'b00000100)
        begin
          testSW[1] = 1;
          testKEY[1] = 1;
        end
      end

// Test Brake:
    3: begin
      if (counter > 8'b00000100)
      begin
        testSW[2] = 1;
      end
    end
  endcase

    counter = counter + 1;
  end
  // End testing
  #10 $finish;
end

// Monitor inputs and outputs
initial
  begin
    $monitor($time, "testSW = %b, testKEY = %b, clock = %b, testLED = %b, testHEX0 = %b,",
           testSW, testKEY, testLED, clock, testHEX0);
  end
endmodule

Project 3/test.vcd
$date
	Tue Apr  7 22:48:07 2020
$end
$version
	Icarus Verilog
$end
$timescale
	100ps
$end
$scope module tb $end
$var wire 10 ! testLED [9:0] $end
$var wire 8 " testHEX0 [7:0] $end
$var reg 1 # clock $end
$var reg 8 $ counter [7:0] $end
$var reg 2 % testKEY [1:0] $end
$var reg 10 & testSW [9:0] $end
$scope module DUT $end
$var wire 1 # ADC_CLK_10 $end
$var wire 2 ' KEY [1:0] $end
$var wire 10 ( SW [9:0] $end
$var wire 3 ) r_LEDS [2:0] $end
$var wire 3 * l_LEDS [2:0] $end
$var wire 1 + clock $end
$var wire 8 , HEX0 [7:0] $end
$var reg 10 - LEDR [9:0] $end
$var reg 3 . left_LEDs [2:0] $end
$var reg 1 / reset $end
$var reg 3 0 right_LEDs [2:0] $end
$scope module B0 $end
$var wire 1 1 hazards $end
$var wire 1 / reset_n $end
$var wire 1 2 turnChange $end
$var wire 8 3 hex [7:0] $end
$var wire 1 + clock $end
$var reg 2 4 blink [1:0] $end
$var reg 2 5 blinkState [1:0] $end
$var reg 3 6 leftLEDs [2:0] $end
$var reg 2 7 next [1:0] $end
$var reg 3 8 rightLEDs [0:2] $end
$scope module H0 $end
$var wire 2 9 val [1:0] $end
$var reg 8 : seg [7:0] $end
$upscope $end
$upscope $end
$scope module C0 $end
$var wire 1 # clock_in $end
$var wire 32 ; divide_by [31:0] $end
$var wire 1 < reset_n $end
$var reg 23 = clock_divider [22:0] $end
$var reg 1 + clock_out $end
$upscope $end
$upscope $end
$upscope $end
$enddefinitions $end
#0
$dumpvars
b0 =
0<
b1 ;
b11000000 :
b0 9
b0 8
b1 7
b0 6
b0 5
b0 4
b11000000 3
02
01
b0 0
0/
b0 .
b0 -
b11000000 ,
0+
b0 *
b0 )
b0 (
b0 '
b0 &
b0 %
b0 $
0#
b11000000 "
b0 !
$end
#100
b1 $
1#
#200
b10 $
0#
#300
b11 $
1#
#400
1<
b100 $
b1 %
b1 '
0#
#500
1+
b101 $
1#
#600
b1110000111 !
b1110000111 -
1/
b110 $
b100 &
b100 (
0#
#700
0+
b111 $
1#
#800
b1000 $
0#
#900
b1 0
b1 .
b1 4
b1 )
b1 8
b1 *
b1 6
b10 7
b11111001 "
b11111001 ,
b11111001 3
b11111001 :
b1 5
b1 9
1+
b1001 $
1#
#1000
b1010 $
0#
#1100
0+
b1011 $
1#
#1200
b1100 $
0#
#1300
b11 0
b11 .
b10 4
b11 )
b11 8
b11 *
b11 6
b11 7
b10100100 "
b10100100 ,
b10100100 3
b10100100 :
b10 5
b10 9
1+
b1101 $
1#
#1400
b1110 $
0#
#1500
0+
b1111 $
1#
#1600
b10000 $
0#
#1700
b111 0
b111 .
b11 4
b111 )
b111 8
b111 *
b111 6
b0 7
b10110000 "
b10110000 ,
b10110000 3
b10110000 :
b11 5
b11 9
1+
b10001 $
1#
#1800
b10010 $
0#
#1900
0+
b10011 $
1#
#2000
b10100 $
0#
#2100
b0 0
b0 .
b0 4
b0 )
b0 8
b0 *
b0 6
b1 7
b11000000 "
b11000000 ,
b11000000 3
b11000000 :
b0 5
b0 9
1+
b10101 $
1#
#2200
b10110 $
0#
#2300
0+
b10111 $
1#
#2400
b11000 $
0#
#2500
b1 0
b1 .
b1 4
b1 )
b1 8
b1 *
b1 6
b10 7
b11111001 "
b11111001 ,
b11111001 3
b11111001 :
b1 5
b1 9
1+
b11001 $
1#
#2600
b11010 $
0#
#2700
0+
b11011 $
1#
#2800
b11100 $
0#
#2900
b11 0
b11 .
b10 4
b11 )
b11 8
b11 *
b11 6
b11 7
b10100100 "
b10100100 ,
b10100100 3
b10100100 :
b10 5
b10 9
1+
b11101 $
1#
#3000
b11110 $
0#
#3100
0+
b11111 $
1#
#3200
b100000 $
0#
